[
  {
    "algo": "agem",
    "metrics_dir": "/home/lunet/wsmr11/repos/La-MAML/logs/00_sync/full-cil_10epochs/saved_models/agem/full-tasks_CIL_all-2026-04-17_11-04-10-7802/0/metrics",
    "task_index": 0,
    "task_name": "t2-rcn",
    "zero_shot_rec_cls": 0.0002467860422405877,
    "zero_shot_prec_cls": 0.006379585326953749,
    "zero_shot_f1_cls": 0.0004751899723864897,
    "zero_shot_det": 0.502293057783586,
    "zero_shot_pfa": 0.0625910059546225,
    "zero_shot_total_f1_zs": 0.10654823493637647,
    "baseline_total_f1_zs": 0.10618367013302889,
    "forward_transfer_total_f1_zs": 0.0003645648033475807
  },
  {
    "algo": "agem",
    "metrics_dir": "/home/lunet/wsmr11/repos/La-MAML/logs/00_sync/full-cil_10epochs/saved_models/agem/full-tasks_CIL_all-2026-04-17_11-04-10-7802/0/metrics",
    "task_index": 1,
    "task_name": "t0-rcn",
    "zero_shot_rec_cls": 0.3954049912471574,
    "zero_shot_prec_cls": 0.21682157055605267,
    "zero_shot_f1_cls": 0.2800673363645014,
    "zero_shot_det": 0.7034287908686662,
    "zero_shot_pfa": 0.5532703151705389,
    "zero_shot_total_f1_zs": 0.24957738875581248,
    "baseline_total_f1_zs": 0.05518635966476692,
    "forward_transfer_total_f1_zs": 0.19439102909104555
  },
  {
    "algo": "agem",
    "metrics_dir": "/home/lunet/wsmr11/repos/La-MAML/logs/00_sync/full-cil_10epochs/saved_models/agem/full-tasks_CIL_all-2026-04-17_11-04-10-7802/0/metrics",
    "task_index": 2,
    "task_name": "t2-uclresm-25noise",
    "zero_shot_rec_cls": 0.06573991739137562,
    "zero_shot_prec_cls": 0.010236125592827052,
    "zero_shot_f1_cls": 0.017714058917759474,
    "zero_shot_det": 0.42164927967791227,
    "zero_shot_pfa": 0.8930756430322865,
    "zero_shot_total_f1_zs": 0.01728662660093936,
    "baseline_total_f1_zs": 0.032515819509912905,
    "forward_transfer_total_f1_zs": -0.015229192908973545
  },
  {
    "algo": "agem",
    "metrics_dir": "/home/lunet/wsmr11/repos/La-MAML/logs/00_sync/full-cil_10epochs/saved_models/agem/full-tasks_CIL_all-2026-04-17_11-04-10-7802/0/metrics",
    "task_index": 3,
    "task_name": "t0-deeprad",
    "zero_shot_rec_cls": 0.09540379353593378,
    "zero_shot_prec_cls": 0.08749033988037892,
    "zero_shot_f1_cls": 0.09127586726181852,
    "zero_shot_det": 0.6082008399078955,
    "zero_shot_pfa": 0.7368865740515854,
    "zero_shot_total_f1_zs": 0.09294818887563194,
    "baseline_total_f1_zs": 0.024830732651589266,
    "forward_transfer_total_f1_zs": 0.06811745622404268
  },
  {
    "algo": "agem",
    "metrics_dir": "/home/lunet/wsmr11/repos/La-MAML/logs/00_sync/full-cil_10epochs/saved_models/agem/full-tasks_CIL_all-2026-04-17_11-04-10-7802/0/metrics",
    "task_index": 4,
    "task_name": "t1-deeprad",
    "zero_shot_rec_cls": 0.07353327208992387,
    "zero_shot_prec_cls": 0.018747218686718595,
    "zero_shot_f1_cls": 0.029877264869699053,
    "zero_shot_det": 0.4222546927163876,
    "zero_shot_pfa": 0.6864317308506899,
    "zero_shot_total_f1_zs": 0.025352377207666553,
    "baseline_total_f1_zs": 0.020725841024185905,
    "forward_transfer_total_f1_zs": 0.004626536183480648
  },
  {
    "algo": "agem",
    "metrics_dir": "/home/lunet/wsmr11/repos/La-MAML/logs/00_sync/full-cil_10epochs/saved_models/agem/full-tasks_CIL_all-2026-04-17_11-04-10-7802/0/metrics",
    "task_index": 5,
    "task_name": "t1-uclresm-25noise",
    "zero_shot_rec_cls": 0.04433560751060819,
    "zero_shot_prec_cls": 0.006465185239805576,
    "zero_shot_f1_cls": 0.011284781191650307,
    "zero_shot_det": 0.5045888249223365,
    "zero_shot_pfa": 0.4789133709686982,
    "zero_shot_total_f1_zs": 0.017681432349442045,
    "baseline_total_f1_zs": 0.016817452807013872,
    "forward_transfer_total_f1_zs": 0.0008639795424281727
  },
  {
    "algo": "agem",
    "metrics_dir": "/home/lunet/wsmr11/repos/La-MAML/logs/00_sync/full-cil_10epochs/saved_models/agem/full-tasks_CIL_all-2026-04-17_11-04-10-7802/0/metrics",
    "task_index": 6,
    "task_name": "t3-deeprad",
    "zero_shot_rec_cls": 0.10770808262664258,
    "zero_shot_prec_cls": 0.029344880253930353,
    "zero_shot_f1_cls": 0.04612349445977989,
    "zero_shot_det": 0.572001192698601,
    "zero_shot_pfa": 0.8154336066297857,
    "zero_shot_total_f1_zs": 0.04388124153584037,
    "baseline_total_f1_zs": 0.01535554160702819,
    "forward_transfer_total_f1_zs": 0.02852569992881218
  },
  {
    "algo": "agem",
    "metrics_dir": "/home/lunet/wsmr11/repos/La-MAML/logs/00_sync/full-cil_10epochs/saved_models/agem/full-tasks_CIL_all-2026-04-17_11-04-10-7802/0/metrics",
    "task_index": 7,
    "task_name": "t0-uclresm-25noise",
    "zero_shot_rec_cls": 0.03871831786290328,
    "zero_shot_prec_cls": 0.0032391916759738747,
    "zero_shot_f1_cls": 0.005978241049460688,
    "zero_shot_det": 0.3880001176691026,
    "zero_shot_pfa": 0.5307491389193518,
    "zero_shot_total_f1_zs": 0.011696992871977223,
    "baseline_total_f1_zs": 0.012209570319375604,
    "forward_transfer_total_f1_zs": -0.0005125774473983807
  },
  {
    "algo": "agem",
    "metrics_dir": "/home/lunet/wsmr11/repos/La-MAML/logs/00_sync/full-cil_10epochs/saved_models/agem/full-tasks_CIL_all-2026-04-17_11-04-10-7802/0/metrics",
    "task_index": 8,
    "task_name": "t1-rcn",
    "zero_shot_rec_cls": 0.09426527469718797,
    "zero_shot_prec_cls": 0.017958223776316756,
    "zero_shot_f1_cls": 0.030169027349432342,
    "zero_shot_det": 0.5476594417996996,
    "zero_shot_pfa": 0.8717105961872211,
    "zero_shot_total_f1_zs": 0.028595677255798434,
    "baseline_total_f1_zs": 0.011909859158956981,
    "forward_transfer_total_f1_zs": 0.016685818096841453
  },
  {
    "algo": "agem",
    "metrics_dir": "/home/lunet/wsmr11/repos/La-MAML/logs/00_sync/full-cil_10epochs/saved_models/agem/full-tasks_CIL_all-2026-04-17_11-04-10-7802/0/metrics",
    "task_index": 9,
    "task_name": "t2-deeprad",
    "zero_shot_rec_cls": 0.011982135163185975,
    "zero_shot_prec_cls": 0.00046434419166025,
    "zero_shot_f1_cls": 0.0008940415531315827,
    "zero_shot_det": 0.6151891033713407,
    "zero_shot_pfa": 0.5675708841189521,
    "zero_shot_total_f1_zs": 0.011701023377187671,
    "baseline_total_f1_zs": 0.008421412506710328,
    "forward_transfer_total_f1_zs": 0.0032796108704773435
  },
  {
    "algo": "gem",
    "metrics_dir": "/home/lunet/wsmr11/repos/La-MAML/logs/00_sync/full-cil_10epochs/saved_models/gem/full-tasks_CIL_all-2026-04-18_11-09-36-8029/0/metrics",
    "task_index": 0,
    "task_name": "t2-rcn",
    "zero_shot_rec_cls": 0.0002467860422405877,
    "zero_shot_prec_cls": 0.006379585326953749,
    "zero_shot_f1_cls": 0.0004751899723864897,
    "zero_shot_det": 0.502293057783586,
    "zero_shot_pfa": 0.0625910059546225,
    "zero_shot_total_f1_zs": 0.10654823493637647,
    "baseline_total_f1_zs": 0.10618367013302889,
    "forward_transfer_total_f1_zs": 0.0003645648033475807
  },
  {
    "algo": "gem",
    "metrics_dir": "/home/lunet/wsmr11/repos/La-MAML/logs/00_sync/full-cil_10epochs/saved_models/gem/full-tasks_CIL_all-2026-04-18_11-09-36-8029/0/metrics",
    "task_index": 1,
    "task_name": "t0-rcn",
    "zero_shot_rec_cls": 0.34579245729020675,
    "zero_shot_prec_cls": 0.197979144115584,
    "zero_shot_f1_cls": 0.2517957707204778,
    "zero_shot_det": 0.7859820985398677,
    "zero_shot_pfa": 0.33083378099209043,
    "zero_shot_total_f1_zs": 0.2463448508581924,
    "baseline_total_f1_zs": 0.05518635966476692,
    "forward_transfer_total_f1_zs": 0.19115849119342548
  },
  {
    "algo": "gem",
    "metrics_dir": "/home/lunet/wsmr11/repos/La-MAML/logs/00_sync/full-cil_10epochs/saved_models/gem/full-tasks_CIL_all-2026-04-18_11-09-36-8029/0/metrics",
    "task_index": 2,
    "task_name": "t2-uclresm-25noise",
    "zero_shot_rec_cls": 0.06514312059849957,
    "zero_shot_prec_cls": 0.00928371392074966,
    "zero_shot_f1_cls": 0.01625139909409827,
    "zero_shot_det": 0.5430383837933195,
    "zero_shot_pfa": 0.8331068887258786,
    "zero_shot_total_f1_zs": 0.02329736221902322,
    "baseline_total_f1_zs": 0.032515819509912905,
    "forward_transfer_total_f1_zs": -0.009218457290889683
  },
  {
    "algo": "gem",
    "metrics_dir": "/home/lunet/wsmr11/repos/La-MAML/logs/00_sync/full-cil_10epochs/saved_models/gem/full-tasks_CIL_all-2026-04-18_11-09-36-8029/0/metrics",
    "task_index": 3,
    "task_name": "t0-deeprad",
    "zero_shot_rec_cls": 0.04909423482532441,
    "zero_shot_prec_cls": 0.05132713011785919,
    "zero_shot_f1_cls": 0.050185857966416815,
    "zero_shot_det": 0.6207301827181062,
    "zero_shot_pfa": 0.6281585571854,
    "zero_shot_total_f1_zs": 0.060872749687705646,
    "baseline_total_f1_zs": 0.024830732651589266,
    "forward_transfer_total_f1_zs": 0.03604201703611638
  },
  {
    "algo": "gem",
    "metrics_dir": "/home/lunet/wsmr11/repos/La-MAML/logs/00_sync/full-cil_10epochs/saved_models/gem/full-tasks_CIL_all-2026-04-18_11-09-36-8029/0/metrics",
    "task_index": 4,
    "task_name": "t1-deeprad",
    "zero_shot_rec_cls": 0.05669596315245238,
    "zero_shot_prec_cls": 0.05175648630991604,
    "zero_shot_f1_cls": 0.054113740266338535,
    "zero_shot_det": 0.38293184145196746,
    "zero_shot_pfa": 0.731140368296733,
    "zero_shot_total_f1_zs": 0.019641011866448427,
    "baseline_total_f1_zs": 0.020725841024185905,
    "forward_transfer_total_f1_zs": -0.0010848291577374783
  },
  {
    "algo": "gem",
    "metrics_dir": "/home/lunet/wsmr11/repos/La-MAML/logs/00_sync/full-cil_10epochs/saved_models/gem/full-tasks_CIL_all-2026-04-18_11-09-36-8029/0/metrics",
    "task_index": 5,
    "task_name": "t1-uclresm-25noise",
    "zero_shot_rec_cls": 0.04309503352724524,
    "zero_shot_prec_cls": 0.02136771668427318,
    "zero_shot_f1_cls": 0.0285697542809736,
    "zero_shot_det": 0.47829589257162913,
    "zero_shot_pfa": 0.450059466036529,
    "zero_shot_total_f1_zs": 0.021729254012841457,
    "baseline_total_f1_zs": 0.016817452807013872,
    "forward_transfer_total_f1_zs": 0.0049118012058275845
  },
  {
    "algo": "gem",
    "metrics_dir": "/home/lunet/wsmr11/repos/La-MAML/logs/00_sync/full-cil_10epochs/saved_models/gem/full-tasks_CIL_all-2026-04-18_11-09-36-8029/0/metrics",
    "task_index": 6,
    "task_name": "t3-deeprad",
    "zero_shot_rec_cls": 0.04298096405094765,
    "zero_shot_prec_cls": 0.01852081899594206,
    "zero_shot_f1_cls": 0.025886815504252335,
    "zero_shot_det": 0.4829952544834652,
    "zero_shot_pfa": 0.9410640079678246,
    "zero_shot_total_f1_zs": 0.01866631593332412,
    "baseline_total_f1_zs": 0.01535554160702819,
    "forward_transfer_total_f1_zs": 0.0033107743262959285
  },
  {
    "algo": "gem",
    "metrics_dir": "/home/lunet/wsmr11/repos/La-MAML/logs/00_sync/full-cil_10epochs/saved_models/gem/full-tasks_CIL_all-2026-04-18_11-09-36-8029/0/metrics",
    "task_index": 7,
    "task_name": "t0-uclresm-25noise",
    "zero_shot_rec_cls": 0.05156400276105329,
    "zero_shot_prec_cls": 0.02655437858988359,
    "zero_shot_f1_cls": 0.035055771183369264,
    "zero_shot_det": 0.5571587206436037,
    "zero_shot_pfa": 0.4506755417252589,
    "zero_shot_total_f1_zs": 0.02919264401134362,
    "baseline_total_f1_zs": 0.012209570319375604,
    "forward_transfer_total_f1_zs": 0.01698307369196802
  },
  {
    "algo": "gem",
    "metrics_dir": "/home/lunet/wsmr11/repos/La-MAML/logs/00_sync/full-cil_10epochs/saved_models/gem/full-tasks_CIL_all-2026-04-18_11-09-36-8029/0/metrics",
    "task_index": 8,
    "task_name": "t1-rcn",
    "zero_shot_rec_cls": 0.03924211563152758,
    "zero_shot_prec_cls": 0.009735531885770497,
    "zero_shot_f1_cls": 0.015600703070146379,
    "zero_shot_det": 0.49562886657503424,
    "zero_shot_pfa": 0.8984172856496085,
    "zero_shot_total_f1_zs": 0.014898600542976618,
    "baseline_total_f1_zs": 0.011909859158956981,
    "forward_transfer_total_f1_zs": 0.002988741384019637
  },
  {
    "algo": "gem",
    "metrics_dir": "/home/lunet/wsmr11/repos/La-MAML/logs/00_sync/full-cil_10epochs/saved_models/gem/full-tasks_CIL_all-2026-04-18_11-09-36-8029/0/metrics",
    "task_index": 9,
    "task_name": "t2-deeprad",
    "zero_shot_rec_cls": 0.006495138491735415,
    "zero_shot_prec_cls": 0.0223552406705258,
    "zero_shot_f1_cls": 0.010065752228384975,
    "zero_shot_det": 0.6551058508715536,
    "zero_shot_pfa": 0.35845285058433335,
    "zero_shot_total_f1_zs": 0.020622252327512164,
    "baseline_total_f1_zs": 0.008421412506710328,
    "forward_transfer_total_f1_zs": 0.012200839820801836
  },
  {
    "algo": "si",
    "metrics_dir": "/home/lunet/wsmr11/repos/La-MAML/logs/00_sync/full-cil_10epochs/saved_models/si/full-tasks_CIL_all-2026-04-17_18-33-04-0892/0/metrics",
    "task_index": 0,
    "task_name": "t2-rcn",
    "zero_shot_rec_cls": 0.0002467860422405877,
    "zero_shot_prec_cls": 0.006379585326953749,
    "zero_shot_f1_cls": 0.0004751899723864897,
    "zero_shot_det": 0.502293057783586,
    "zero_shot_pfa": 0.0625910059546225,
    "zero_shot_total_f1_zs": 0.10654823493637647,
    "baseline_total_f1_zs": 0.10618367013302889,
    "forward_transfer_total_f1_zs": 0.0003645648033475807
  },
  {
    "algo": "si",
    "metrics_dir": "/home/lunet/wsmr11/repos/La-MAML/logs/00_sync/full-cil_10epochs/saved_models/si/full-tasks_CIL_all-2026-04-17_18-33-04-0892/0/metrics",
    "task_index": 1,
    "task_name": "t0-rcn",
    "zero_shot_rec_cls": 0.3772737644333211,
    "zero_shot_prec_cls": 0.21955192287162245,
    "zero_shot_f1_cls": 0.2775724376220731,
    "zero_shot_det": 0.7835281391513427,
    "zero_shot_pfa": 0.32540632797440233,
    "zero_shot_total_f1_zs": 0.26726681524697893,
    "baseline_total_f1_zs": 0.05518635966476692,
    "forward_transfer_total_f1_zs": 0.212080455582212
  },
  {
    "algo": "si",
    "metrics_dir": "/home/lunet/wsmr11/repos/La-MAML/logs/00_sync/full-cil_10epochs/saved_models/si/full-tasks_CIL_all-2026-04-17_18-33-04-0892/0/metrics",
    "task_index": 2,
    "task_name": "t2-uclresm-25noise",
    "zero_shot_rec_cls": 0.06505968053950938,
    "zero_shot_prec_cls": 0.009275508239848337,
    "zero_shot_f1_cls": 0.016236229781222973,
    "zero_shot_det": 0.4219723502539807,
    "zero_shot_pfa": 0.8713765627477278,
    "zero_shot_total_f1_zs": 0.017006416957365936,
    "baseline_total_f1_zs": 0.032515819509912905,
    "forward_transfer_total_f1_zs": -0.015509402552546969
  },
  {
    "algo": "si",
    "metrics_dir": "/home/lunet/wsmr11/repos/La-MAML/logs/00_sync/full-cil_10epochs/saved_models/si/full-tasks_CIL_all-2026-04-17_18-33-04-0892/0/metrics",
    "task_index": 3,
    "task_name": "t0-deeprad",
    "zero_shot_rec_cls": 0.06698291538954144,
    "zero_shot_prec_cls": 0.06607925128611089,
    "zero_shot_f1_cls": 0.06652801481417203,
    "zero_shot_det": 0.5455122518020773,
    "zero_shot_pfa": 0.7994891062537015,
    "zero_shot_total_f1_zs": 0.06594309611075577,
    "baseline_total_f1_zs": 0.024830732651589266,
    "forward_transfer_total_f1_zs": 0.04111236345916651
  },
  {
    "algo": "si",
    "metrics_dir": "/home/lunet/wsmr11/repos/La-MAML/logs/00_sync/full-cil_10epochs/saved_models/si/full-tasks_CIL_all-2026-04-17_18-33-04-0892/0/metrics",
    "task_index": 4,
    "task_name": "t1-deeprad",
    "zero_shot_rec_cls": 0.07450265083399898,
    "zero_shot_prec_cls": 0.01759248569058222,
    "zero_shot_f1_cls": 0.028463757548320347,
    "zero_shot_det": 0.5684180705408747,
    "zero_shot_pfa": 0.5833412780413375,
    "zero_shot_total_f1_zs": 0.02794924277361248,
    "baseline_total_f1_zs": 0.020725841024185905,
    "forward_transfer_total_f1_zs": 0.007223401749426574
  },
  {
    "algo": "si",
    "metrics_dir": "/home/lunet/wsmr11/repos/La-MAML/logs/00_sync/full-cil_10epochs/saved_models/si/full-tasks_CIL_all-2026-04-17_18-33-04-0892/0/metrics",
    "task_index": 5,
    "task_name": "t1-uclresm-25noise",
    "zero_shot_rec_cls": 0.042712435809662753,
    "zero_shot_prec_cls": 0.004359593774420835,
    "zero_shot_f1_cls": 0.00791165670532795,
    "zero_shot_det": 0.4740033634938854,
    "zero_shot_pfa": 0.48438331160399944,
    "zero_shot_total_f1_zs": 0.016196893610557716,
    "baseline_total_f1_zs": 0.016817452807013872,
    "forward_transfer_total_f1_zs": -0.0006205591964561566
  },
  {
    "algo": "si",
    "metrics_dir": "/home/lunet/wsmr11/repos/La-MAML/logs/00_sync/full-cil_10epochs/saved_models/si/full-tasks_CIL_all-2026-04-17_18-33-04-0892/0/metrics",
    "task_index": 6,
    "task_name": "t3-deeprad",
    "zero_shot_rec_cls": 0.07144892868005374,
    "zero_shot_prec_cls": 0.023268102013736337,
    "zero_shot_f1_cls": 0.03510416129226609,
    "zero_shot_det": 0.4941404993577445,
    "zero_shot_pfa": 0.9044880215775248,
    "zero_shot_total_f1_zs": 0.0299040104684526,
    "baseline_total_f1_zs": 0.01535554160702819,
    "forward_transfer_total_f1_zs": 0.014548468861424411
  },
  {
    "algo": "si",
    "metrics_dir": "/home/lunet/wsmr11/repos/La-MAML/logs/00_sync/full-cil_10epochs/saved_models/si/full-tasks_CIL_all-2026-04-17_18-33-04-0892/0/metrics",
    "task_index": 7,
    "task_name": "t0-uclresm-25noise",
    "zero_shot_rec_cls": 0.040684807668302285,
    "zero_shot_prec_cls": 0.013395091357512377,
    "zero_shot_f1_cls": 0.020154501964568697,
    "zero_shot_det": 0.47511265954567106,
    "zero_shot_pfa": 0.4673671311122518,
    "zero_shot_total_f1_zs": 0.01572873129367259,
    "baseline_total_f1_zs": 0.012209570319375604,
    "forward_transfer_total_f1_zs": 0.0035191609742969854
  },
  {
    "algo": "si",
    "metrics_dir": "/home/lunet/wsmr11/repos/La-MAML/logs/00_sync/full-cil_10epochs/saved_models/si/full-tasks_CIL_all-2026-04-17_18-33-04-0892/0/metrics",
    "task_index": 8,
    "task_name": "t1-rcn",
    "zero_shot_rec_cls": 0.06541528244267267,
    "zero_shot_prec_cls": 0.01367881992502032,
    "zero_shot_f1_cls": 0.022626310738514864,
    "zero_shot_det": 0.5624587549955563,
    "zero_shot_pfa": 0.8293003085555448,
    "zero_shot_total_f1_zs": 0.023852187469364426,
    "baseline_total_f1_zs": 0.011909859158956981,
    "forward_transfer_total_f1_zs": 0.011942328310407445
  },
  {
    "algo": "si",
    "metrics_dir": "/home/lunet/wsmr11/repos/La-MAML/logs/00_sync/full-cil_10epochs/saved_models/si/full-tasks_CIL_all-2026-04-17_18-33-04-0892/0/metrics",
    "task_index": 9,
    "task_name": "t2-deeprad",
    "zero_shot_rec_cls": 0.007115354440414779,
    "zero_shot_prec_cls": 0.0004811092354265429,
    "zero_shot_f1_cls": 0.0009012779842556619,
    "zero_shot_det": 0.5460480969042945,
    "zero_shot_pfa": 0.6602100994083187,
    "zero_shot_total_f1_zs": 0.00915734774063231,
    "baseline_total_f1_zs": 0.008421412506710328,
    "forward_transfer_total_f1_zs": 0.0007359352339219825
  },
  {
    "algo": "smaml",
    "metrics_dir": "/home/lunet/wsmr11/repos/La-MAML/logs/00_sync/full-cil_10epochs/saved_models/smaml/full-tasks_CIL_all-2026-04-17_11-04-10-7961/0/metrics",
    "task_index": 0,
    "task_name": "t2-rcn",
    "zero_shot_rec_cls": 0.0002467860422405877,
    "zero_shot_prec_cls": 0.006379585326953749,
    "zero_shot_f1_cls": 0.0004751899723864897,
    "zero_shot_det": 0.502293057783586,
    "zero_shot_pfa": 0.0625910059546225,
    "zero_shot_total_f1_zs": 0.10654823493637647,
    "baseline_total_f1_zs": 0.10618367013302889,
    "forward_transfer_total_f1_zs": 0.0003645648033475807
  },
  {
    "algo": "smaml",
    "metrics_dir": "/home/lunet/wsmr11/repos/La-MAML/logs/00_sync/full-cil_10epochs/saved_models/smaml/full-tasks_CIL_all-2026-04-17_11-04-10-7961/0/metrics",
    "task_index": 1,
    "task_name": "t0-rcn",
    "zero_shot_rec_cls": 0.25310048840735727,
    "zero_shot_prec_cls": 0.18461312321942844,
    "zero_shot_f1_cls": 0.21349882851294733,
    "zero_shot_det": 0.7127668169354177,
    "zero_shot_pfa": 0.31993387202252005,
    "zero_shot_total_f1_zs": 0.1792737400470467,
    "baseline_total_f1_zs": 0.05518635966476692,
    "forward_transfer_total_f1_zs": 0.12408738038227976
  },
  {
    "algo": "smaml",
    "metrics_dir": "/home/lunet/wsmr11/repos/La-MAML/logs/00_sync/full-cil_10epochs/saved_models/smaml/full-tasks_CIL_all-2026-04-17_11-04-10-7961/0/metrics",
    "task_index": 2,
    "task_name": "t2-uclresm-25noise",
    "zero_shot_rec_cls": 0.0647938267077937,
    "zero_shot_prec_cls": 0.009247151649908717,
    "zero_shot_f1_cls": 0.01618450633243271,
    "zero_shot_det": 0.3990932619343257,
    "zero_shot_pfa": 0.7854735709002665,
    "zero_shot_total_f1_zs": 0.02001095566494881,
    "baseline_total_f1_zs": 0.032515819509912905,
    "forward_transfer_total_f1_zs": -0.012504863844964093
  },
  {
    "algo": "smaml",
    "metrics_dir": "/home/lunet/wsmr11/repos/La-MAML/logs/00_sync/full-cil_10epochs/saved_models/smaml/full-tasks_CIL_all-2026-04-17_11-04-10-7961/0/metrics",
    "task_index": 3,
    "task_name": "t0-deeprad",
    "zero_shot_rec_cls": 0.021705451609915154,
    "zero_shot_prec_cls": 0.08494713207692918,
    "zero_shot_f1_cls": 0.03457611247582545,
    "zero_shot_det": 0.572204101763335,
    "zero_shot_pfa": 0.8235066469635982,
    "zero_shot_total_f1_zs": 0.039300137885801084,
    "baseline_total_f1_zs": 0.024830732651589266,
    "forward_transfer_total_f1_zs": 0.014469405234211818
  },
  {
    "algo": "smaml",
    "metrics_dir": "/home/lunet/wsmr11/repos/La-MAML/logs/00_sync/full-cil_10epochs/saved_models/smaml/full-tasks_CIL_all-2026-04-17_11-04-10-7961/0/metrics",
    "task_index": 4,
    "task_name": "t1-deeprad",
    "zero_shot_rec_cls": 0.080134725216109,
    "zero_shot_prec_cls": 0.10014350309884887,
    "zero_shot_f1_cls": 0.08902874382573431,
    "zero_shot_det": 0.5736642326718047,
    "zero_shot_pfa": 0.5365440308903715,
    "zero_shot_total_f1_zs": 0.0638467701251711,
    "baseline_total_f1_zs": 0.020725841024185905,
    "forward_transfer_total_f1_zs": 0.0431209291009852
  },
  {
    "algo": "smaml",
    "metrics_dir": "/home/lunet/wsmr11/repos/La-MAML/logs/00_sync/full-cil_10epochs/saved_models/smaml/full-tasks_CIL_all-2026-04-17_11-04-10-7961/0/metrics",
    "task_index": 5,
    "task_name": "t1-uclresm-25noise",
    "zero_shot_rec_cls": 0.06585367973126406,
    "zero_shot_prec_cls": 0.07142514411078278,
    "zero_shot_f1_cls": 0.0685263529128549,
    "zero_shot_det": 0.5922103158819332,
    "zero_shot_pfa": 0.5764888569654133,
    "zero_shot_total_f1_zs": 0.05229594701432582,
    "baseline_total_f1_zs": 0.016817452807013872,
    "forward_transfer_total_f1_zs": 0.035478494207311945
  },
  {
    "algo": "smaml",
    "metrics_dir": "/home/lunet/wsmr11/repos/La-MAML/logs/00_sync/full-cil_10epochs/saved_models/smaml/full-tasks_CIL_all-2026-04-17_11-04-10-7961/0/metrics",
    "task_index": 6,
    "task_name": "t3-deeprad",
    "zero_shot_rec_cls": 0.06267380432029887,
    "zero_shot_prec_cls": 0.10407843450469585,
    "zero_shot_f1_cls": 0.07823572845646987,
    "zero_shot_det": 0.5951202860287675,
    "zero_shot_pfa": 0.7749422806389319,
    "zero_shot_total_f1_zs": 0.06138302997923395,
    "baseline_total_f1_zs": 0.01535554160702819,
    "forward_transfer_total_f1_zs": 0.04602748837220576
  },
  {
    "algo": "smaml",
    "metrics_dir": "/home/lunet/wsmr11/repos/La-MAML/logs/00_sync/full-cil_10epochs/saved_models/smaml/full-tasks_CIL_all-2026-04-17_11-04-10-7961/0/metrics",
    "task_index": 7,
    "task_name": "t0-uclresm-25noise",
    "zero_shot_rec_cls": 0.09215410582917002,
    "zero_shot_prec_cls": 0.12927916291025981,
    "zero_shot_f1_cls": 0.10760447811803613,
    "zero_shot_det": 0.6039233640312305,
    "zero_shot_pfa": 0.42027814824357457,
    "zero_shot_total_f1_zs": 0.08547828643661311,
    "baseline_total_f1_zs": 0.012209570319375604,
    "forward_transfer_total_f1_zs": 0.07326871611723751
  },
  {
    "algo": "smaml",
    "metrics_dir": "/home/lunet/wsmr11/repos/La-MAML/logs/00_sync/full-cil_10epochs/saved_models/smaml/full-tasks_CIL_all-2026-04-17_11-04-10-7961/0/metrics",
    "task_index": 8,
    "task_name": "t1-rcn",
    "zero_shot_rec_cls": 0.0821349817080824,
    "zero_shot_prec_cls": 0.17087045006449167,
    "zero_shot_f1_cls": 0.11094181806432009,
    "zero_shot_det": 0.6077581240582342,
    "zero_shot_pfa": 0.736895260876605,
    "zero_shot_total_f1_zs": 0.08148301292005154,
    "baseline_total_f1_zs": 0.011909859158956981,
    "forward_transfer_total_f1_zs": 0.06957315376109456
  },
  {
    "algo": "smaml",
    "metrics_dir": "/home/lunet/wsmr11/repos/La-MAML/logs/00_sync/full-cil_10epochs/saved_models/smaml/full-tasks_CIL_all-2026-04-17_11-04-10-7961/0/metrics",
    "task_index": 9,
    "task_name": "t2-deeprad",
    "zero_shot_rec_cls": 0.089847116115451,
    "zero_shot_prec_cls": 0.1885208928634669,
    "zero_shot_f1_cls": 0.12169543916646836,
    "zero_shot_det": 0.6464359556528685,
    "zero_shot_pfa": 0.5290759174622228,
    "zero_shot_total_f1_zs": 0.10273850245132371,
    "baseline_total_f1_zs": 0.008421412506710328,
    "forward_transfer_total_f1_zs": 0.09431708994461338
  }
]
