{
  "config": "/home/lunet/wsmr11/repos/La-MAML/configs/models/ucl.yaml",
  "config_chain": [
    "/home/lunet/wsmr11/repos/La-MAML/configs/tuning_defaults.yaml",
    "/home/lunet/wsmr11/repos/La-MAML/configs/tuning_defaults.yaml",
    "/home/lunet/wsmr11/repos/La-MAML/configs/models/ucl.yaml"
  ],
  "base_expt_name": "tuning_sweep_CIL",
  "session_dir": "/home/lunet/wsmr11/repos/La-MAML/scripts/logs/tuning/ucl/2026-04-01_19-26-40-1637",
  "timestamp": "2026-04-01_19-26-40-1637",
  "fixed_overrides": {},
  "search_space": {
    "lr": [
      0.03,
      0.01,
      0.003,
      0.001,
      0.0003,
      0.0001,
      3e-05,
      1e-05
    ],
    "beta": [
      0.0001,
      0.0002,
      0.001,
      0.002,
      0.01,
      0.02,
      0.05,
      0.1,
      0.5
    ]
  },
  "hierarchical": false,
  "lr_first": false,
  "lr_first_keys": null,
  "lr_first_best": null,
  "num_trials": 72,
  "results": [
    {
      "status": "ok",
      "trial": 0,
      "log_dir": "logs/tuning/ucl/2026-04-01_19-26-40-1637/runs/ucl_bresnet/tuning_sweep_CIL_tune_000_beta-1em04_lr-3em02-2026-04-01_19-26-40-1637-trial000/0",
      "tf_dir": "logs/tuning/ucl/2026-04-01_19-26-40-1637/runs/ucl_bresnet/tuning_sweep_CIL_tune_000_beta-1em04_lr-3em02-2026-04-01_19-26-40-1637-trial000/0/tfdir",
      "params": {
        "beta": 0.0001,
        "lr": 0.03
      },
      "trial_params": {
        "beta": 0.0001,
        "lr": 0.03
      },
      "fixed_params": {},
      "val_per_task": [
        0.21231545507907867,
        0.0,
        0.0
      ],
      "val_mean": 0.07077181835969289,
      "val_f1_mean": 0.021418011120868066,
      "val_det_per_task": [
        0.5,
        0.5,
        0.5
      ],
      "val_det_mean": 0.5,
      "val_pfa_per_task": [
        1.0,
        1.0,
        1.0
      ],
      "val_pfa_mean": 1.0,
      "test_per_task": [],
      "test_mean": NaN,
      "test_det_per_task": [],
      "test_det_mean": NaN,
      "test_pfa_per_task": [],
      "test_pfa_mean": NaN,
      "score": 0.021418011120868066,
      "duration_sec": 93.39848589897156
    },
    {
      "status": "ok",
      "trial": 1,
      "log_dir": "logs/tuning/ucl/2026-04-01_19-26-40-1637/runs/ucl_bresnet/tuning_sweep_CIL_tune_001_beta-1em04_lr-1em02-2026-04-01_19-26-40-1637-trial001/0",
      "tf_dir": "logs/tuning/ucl/2026-04-01_19-26-40-1637/runs/ucl_bresnet/tuning_sweep_CIL_tune_001_beta-1em04_lr-1em02-2026-04-01_19-26-40-1637-trial001/0/tfdir",
      "params": {
        "beta": 0.0001,
        "lr": 0.01
      },
      "trial_params": {
        "beta": 0.0001,
        "lr": 0.01
      },
      "fixed_params": {},
      "val_per_task": [
        0.340411514043808,
        0.09646464884281158,
        0.0
      ],
      "val_mean": 0.1456253876288732,
      "val_f1_mean": 0.049620530558970165,
      "val_det_per_task": [
        0.5,
        0.5,
        0.5
      ],
      "val_det_mean": 0.5,
      "val_pfa_per_task": [
        1.0,
        1.0,
        1.0
      ],
      "val_pfa_mean": 1.0,
      "test_per_task": [],
      "test_mean": NaN,
      "test_det_per_task": [],
      "test_det_mean": NaN,
      "test_pfa_per_task": [],
      "test_pfa_mean": NaN,
      "score": 0.049620530558970165,
      "duration_sec": 92.22638130187988
    },
    {
      "status": "ok",
      "trial": 2,
      "log_dir": "logs/tuning/ucl/2026-04-01_19-26-40-1637/runs/ucl_bresnet/tuning_sweep_CIL_tune_002_beta-1em04_lr-3em03-2026-04-01_19-26-40-1637-trial002/0",
      "tf_dir": "logs/tuning/ucl/2026-04-01_19-26-40-1637/runs/ucl_bresnet/tuning_sweep_CIL_tune_002_beta-1em04_lr-3em03-2026-04-01_19-26-40-1637-trial002/0/tfdir",
      "params": {
        "beta": 0.0001,
        "lr": 0.003
      },
      "trial_params": {
        "beta": 0.0001,
        "lr": 0.003
      },
      "fixed_params": {},
      "val_per_task": [
        0.28078392148017883,
        0.09646464884281158,
        0.0
      ],
      "val_mean": 0.1257495234409968,
      "val_f1_mean": 0.045230851317408956,
      "val_det_per_task": [
        0.5,
        0.5,
        0.5
      ],
      "val_det_mean": 0.5,
      "val_pfa_per_task": [
        1.0,
        1.0,
        1.0
      ],
      "val_pfa_mean": 1.0,
      "test_per_task": [],
      "test_mean": NaN,
      "test_det_per_task": [],
      "test_det_mean": NaN,
      "test_pfa_per_task": [],
      "test_pfa_mean": NaN,
      "score": 0.045230851317408956,
      "duration_sec": 92.9362576007843
    },
    {
      "status": "ok",
      "trial": 3,
      "log_dir": "logs/tuning/ucl/2026-04-01_19-26-40-1637/runs/ucl_bresnet/tuning_sweep_CIL_tune_003_beta-1em04_lr-1em03-2026-04-01_19-26-40-1637-trial003/0",
      "tf_dir": "logs/tuning/ucl/2026-04-01_19-26-40-1637/runs/ucl_bresnet/tuning_sweep_CIL_tune_003_beta-1em04_lr-1em03-2026-04-01_19-26-40-1637-trial003/0/tfdir",
      "params": {
        "beta": 0.0001,
        "lr": 0.001
      },
      "trial_params": {
        "beta": 0.0001,
        "lr": 0.001
      },
      "fixed_params": {},
      "val_per_task": [
        0.3277472257614136,
        0.09818878769874573,
        0.0
      ],
      "val_mean": 0.14197867115338644,
      "val_f1_mean": 0.07190167547811346,
      "val_det_per_task": [
        0.5,
        0.5,
        0.5
      ],
      "val_det_mean": 0.5,
      "val_pfa_per_task": [
        1.0,
        1.0,
        1.0
      ],
      "val_pfa_mean": 1.0,
      "test_per_task": [],
      "test_mean": NaN,
      "test_det_per_task": [],
      "test_det_mean": NaN,
      "test_pfa_per_task": [],
      "test_pfa_mean": NaN,
      "score": 0.07190167547811346,
      "duration_sec": 91.88571286201477
    },
    {
      "status": "ok",
      "trial": 4,
      "log_dir": "logs/tuning/ucl/2026-04-01_19-26-40-1637/runs/ucl_bresnet/tuning_sweep_CIL_tune_004_beta-1em04_lr-3em04-2026-04-01_19-26-40-1637-trial004/0",
      "tf_dir": "logs/tuning/ucl/2026-04-01_19-26-40-1637/runs/ucl_bresnet/tuning_sweep_CIL_tune_004_beta-1em04_lr-3em04-2026-04-01_19-26-40-1637-trial004/0/tfdir",
      "params": {
        "beta": 0.0001,
        "lr": 0.0003
      },
      "trial_params": {
        "beta": 0.0001,
        "lr": 0.0003
      },
      "fixed_params": {},
      "val_per_task": [
        0.3516805171966553,
        0.09098108857870102,
        0.0
      ],
      "val_mean": 0.14755386859178543,
      "val_f1_mean": 0.04582905874037235,
      "val_det_per_task": [
        0.5,
        0.5,
        0.5
      ],
      "val_det_mean": 0.5,
      "val_pfa_per_task": [
        1.0,
        1.0,
        1.0
      ],
      "val_pfa_mean": 1.0,
      "test_per_task": [],
      "test_mean": NaN,
      "test_det_per_task": [],
      "test_det_mean": NaN,
      "test_pfa_per_task": [],
      "test_pfa_mean": NaN,
      "score": 0.04582905874037235,
      "duration_sec": 92.3325731754303
    },
    {
      "status": "ok",
      "trial": 5,
      "log_dir": "logs/tuning/ucl/2026-04-01_19-26-40-1637/runs/ucl_bresnet/tuning_sweep_CIL_tune_005_beta-1em04_lr-1em04-2026-04-01_19-26-40-1637-trial005/0",
      "tf_dir": "logs/tuning/ucl/2026-04-01_19-26-40-1637/runs/ucl_bresnet/tuning_sweep_CIL_tune_005_beta-1em04_lr-1em04-2026-04-01_19-26-40-1637-trial005/0/tfdir",
      "params": {
        "beta": 0.0001,
        "lr": 0.0001
      },
      "trial_params": {
        "beta": 0.0001,
        "lr": 0.0001
      },
      "fixed_params": {},
      "val_per_task": [
        0.3529270589351654,
        0.0911712720990181,
        0.0
      ],
      "val_mean": 0.1480327770113945,
      "val_f1_mean": 0.04996734889453999,
      "val_det_per_task": [
        0.5,
        0.5,
        0.5
      ],
      "val_det_mean": 0.5,
      "val_pfa_per_task": [
        1.0,
        1.0,
        1.0
      ],
      "val_pfa_mean": 1.0,
      "test_per_task": [],
      "test_mean": NaN,
      "test_det_per_task": [],
      "test_det_mean": NaN,
      "test_pfa_per_task": [],
      "test_pfa_mean": NaN,
      "score": 0.04996734889453999,
      "duration_sec": 93.17365622520447
    },
    {
      "status": "ok",
      "trial": 6,
      "log_dir": "logs/tuning/ucl/2026-04-01_19-26-40-1637/runs/ucl_bresnet/tuning_sweep_CIL_tune_006_beta-1em04_lr-3em05-2026-04-01_19-26-40-1637-trial006/0",
      "tf_dir": "logs/tuning/ucl/2026-04-01_19-26-40-1637/runs/ucl_bresnet/tuning_sweep_CIL_tune_006_beta-1em04_lr-3em05-2026-04-01_19-26-40-1637-trial006/0/tfdir",
      "params": {
        "beta": 0.0001,
        "lr": 3e-05
      },
      "trial_params": {
        "beta": 0.0001,
        "lr": 3e-05
      },
      "fixed_params": {},
      "val_per_task": [
        0.29142943024635315,
        0.09721894562244415,
        0.0
      ],
      "val_mean": 0.12954945862293243,
      "val_f1_mean": 0.060800006473725604,
      "val_det_per_task": [
        0.5,
        0.5,
        0.5
      ],
      "val_det_mean": 0.5,
      "val_pfa_per_task": [
        1.0,
        1.0,
        1.0
      ],
      "val_pfa_mean": 1.0,
      "test_per_task": [],
      "test_mean": NaN,
      "test_det_per_task": [],
      "test_det_mean": NaN,
      "test_pfa_per_task": [],
      "test_pfa_mean": NaN,
      "score": 0.060800006473725604,
      "duration_sec": 91.84091711044312
    },
    {
      "status": "ok",
      "trial": 7,
      "log_dir": "logs/tuning/ucl/2026-04-01_19-26-40-1637/runs/ucl_bresnet/tuning_sweep_CIL_tune_007_beta-1em04_lr-1em05-2026-04-01_19-26-40-1637-trial007/0",
      "tf_dir": "logs/tuning/ucl/2026-04-01_19-26-40-1637/runs/ucl_bresnet/tuning_sweep_CIL_tune_007_beta-1em04_lr-1em05-2026-04-01_19-26-40-1637-trial007/0/tfdir",
      "params": {
        "beta": 0.0001,
        "lr": 1e-05
      },
      "trial_params": {
        "beta": 0.0001,
        "lr": 1e-05
      },
      "fixed_params": {},
      "val_per_task": [
        0.29970669746398926,
        0.09646464884281158,
        0.0
      ],
      "val_mean": 0.13205711543560028,
      "val_f1_mean": 0.055064340969462194,
      "val_det_per_task": [
        0.5,
        0.5,
        0.5
      ],
      "val_det_mean": 0.5,
      "val_pfa_per_task": [
        1.0,
        1.0,
        1.0
      ],
      "val_pfa_mean": 1.0,
      "test_per_task": [],
      "test_mean": NaN,
      "test_det_per_task": [],
      "test_det_mean": NaN,
      "test_pfa_per_task": [],
      "test_pfa_mean": NaN,
      "score": 0.055064340969462194,
      "duration_sec": 93.11052751541138
    },
    {
      "status": "ok",
      "trial": 8,
      "log_dir": "logs/tuning/ucl/2026-04-01_19-26-40-1637/runs/ucl_bresnet/tuning_sweep_CIL_tune_008_beta-2em04_lr-3em02-2026-04-01_19-26-40-1637-trial008/0",
      "tf_dir": "logs/tuning/ucl/2026-04-01_19-26-40-1637/runs/ucl_bresnet/tuning_sweep_CIL_tune_008_beta-2em04_lr-3em02-2026-04-01_19-26-40-1637-trial008/0/tfdir",
      "params": {
        "beta": 0.0002,
        "lr": 0.03
      },
      "trial_params": {
        "beta": 0.0002,
        "lr": 0.03
      },
      "fixed_params": {},
      "val_per_task": [
        0.20745643973350525,
        0.0,
        0.0
      ],
      "val_mean": 0.06915214657783508,
      "val_f1_mean": 0.020253327678575007,
      "val_det_per_task": [
        0.5,
        0.5,
        0.5
      ],
      "val_det_mean": 0.5,
      "val_pfa_per_task": [
        1.0,
        1.0,
        1.0
      ],
      "val_pfa_mean": 1.0,
      "test_per_task": [],
      "test_mean": NaN,
      "test_det_per_task": [],
      "test_det_mean": NaN,
      "test_pfa_per_task": [],
      "test_pfa_mean": NaN,
      "score": 0.020253327678575007,
      "duration_sec": 92.87253952026367
    },
    {
      "status": "ok",
      "trial": 9,
      "log_dir": "logs/tuning/ucl/2026-04-01_19-26-40-1637/runs/ucl_bresnet/tuning_sweep_CIL_tune_009_beta-2em04_lr-1em02-2026-04-01_19-26-40-1637-trial009/0",
      "tf_dir": "logs/tuning/ucl/2026-04-01_19-26-40-1637/runs/ucl_bresnet/tuning_sweep_CIL_tune_009_beta-2em04_lr-1em02-2026-04-01_19-26-40-1637-trial009/0/tfdir",
      "params": {
        "beta": 0.0002,
        "lr": 0.01
      },
      "trial_params": {
        "beta": 0.0002,
        "lr": 0.01
      },
      "fixed_params": {},
      "val_per_task": [
        0.35490989685058594,
        0.14384318888187408,
        0.0
      ],
      "val_mean": 0.16625102857748666,
      "val_f1_mean": 0.06883950401330692,
      "val_det_per_task": [
        0.5,
        0.5,
        0.5
      ],
      "val_det_mean": 0.5,
      "val_pfa_per_task": [
        1.0,
        1.0,
        1.0
      ],
      "val_pfa_mean": 1.0,
      "test_per_task": [],
      "test_mean": NaN,
      "test_det_per_task": [],
      "test_det_mean": NaN,
      "test_pfa_per_task": [],
      "test_pfa_mean": NaN,
      "score": 0.06883950401330692,
      "duration_sec": 92.06702637672424
    },
    {
      "status": "ok",
      "trial": 10,
      "log_dir": "logs/tuning/ucl/2026-04-01_19-26-40-1637/runs/ucl_bresnet/tuning_sweep_CIL_tune_010_beta-2em04_lr-3em03-2026-04-01_19-26-40-1637-trial010/0",
      "tf_dir": "logs/tuning/ucl/2026-04-01_19-26-40-1637/runs/ucl_bresnet/tuning_sweep_CIL_tune_010_beta-2em04_lr-3em03-2026-04-01_19-26-40-1637-trial010/0/tfdir",
      "params": {
        "beta": 0.0002,
        "lr": 0.003
      },
      "trial_params": {
        "beta": 0.0002,
        "lr": 0.003
      },
      "fixed_params": {},
      "val_per_task": [
        0.30647239089012146,
        0.09646464884281158,
        0.0
      ],
      "val_mean": 0.13431234657764435,
      "val_f1_mean": 0.04979677297503427,
      "val_det_per_task": [
        0.5,
        0.5,
        0.5
      ],
      "val_det_mean": 0.5,
      "val_pfa_per_task": [
        1.0,
        1.0,
        1.0
      ],
      "val_pfa_mean": 1.0,
      "test_per_task": [],
      "test_mean": NaN,
      "test_det_per_task": [],
      "test_det_mean": NaN,
      "test_pfa_per_task": [],
      "test_pfa_mean": NaN,
      "score": 0.04979677297503427,
      "duration_sec": 93.17954325675964
    },
    {
      "status": "ok",
      "trial": 11,
      "log_dir": "logs/tuning/ucl/2026-04-01_19-26-40-1637/runs/ucl_bresnet/tuning_sweep_CIL_tune_011_beta-2em04_lr-1em03-2026-04-01_19-26-40-1637-trial011/0",
      "tf_dir": "logs/tuning/ucl/2026-04-01_19-26-40-1637/runs/ucl_bresnet/tuning_sweep_CIL_tune_011_beta-2em04_lr-1em03-2026-04-01_19-26-40-1637-trial011/0/tfdir",
      "params": {
        "beta": 0.0002,
        "lr": 0.001
      },
      "trial_params": {
        "beta": 0.0002,
        "lr": 0.001
      },
      "fixed_params": {},
      "val_per_task": [
        0.3048902451992035,
        0.09776369482278824,
        0.0
      ],
      "val_mean": 0.13421798000733057,
      "val_f1_mean": 0.06823047777805598,
      "val_det_per_task": [
        0.5,
        0.5,
        0.5
      ],
      "val_det_mean": 0.5,
      "val_pfa_per_task": [
        1.0,
        1.0,
        1.0
      ],
      "val_pfa_mean": 1.0,
      "test_per_task": [],
      "test_mean": NaN,
      "test_det_per_task": [],
      "test_det_mean": NaN,
      "test_pfa_per_task": [],
      "test_pfa_mean": NaN,
      "score": 0.06823047777805598,
      "duration_sec": 92.30602407455444
    },
    {
      "status": "ok",
      "trial": 12,
      "log_dir": "logs/tuning/ucl/2026-04-01_19-26-40-1637/runs/ucl_bresnet/tuning_sweep_CIL_tune_012_beta-2em04_lr-3em04-2026-04-01_19-26-40-1637-trial012/0",
      "tf_dir": "logs/tuning/ucl/2026-04-01_19-26-40-1637/runs/ucl_bresnet/tuning_sweep_CIL_tune_012_beta-2em04_lr-3em04-2026-04-01_19-26-40-1637-trial012/0/tfdir",
      "params": {
        "beta": 0.0002,
        "lr": 0.0003
      },
      "trial_params": {
        "beta": 0.0002,
        "lr": 0.0003
      },
      "fixed_params": {},
      "val_per_task": [
        0.34847286343574524,
        0.08619602769613266,
        0.0
      ],
      "val_mean": 0.14488963037729263,
      "val_f1_mean": 0.04541850908646944,
      "val_det_per_task": [
        0.5,
        0.5,
        0.5
      ],
      "val_det_mean": 0.5,
      "val_pfa_per_task": [
        1.0,
        1.0,
        1.0
      ],
      "val_pfa_mean": 1.0,
      "test_per_task": [],
      "test_mean": NaN,
      "test_det_per_task": [],
      "test_det_mean": NaN,
      "test_pfa_per_task": [],
      "test_pfa_mean": NaN,
      "score": 0.04541850908646944,
      "duration_sec": 91.60125803947449
    },
    {
      "status": "ok",
      "trial": 13,
      "log_dir": "logs/tuning/ucl/2026-04-01_19-26-40-1637/runs/ucl_bresnet/tuning_sweep_CIL_tune_013_beta-2em04_lr-1em04-2026-04-01_19-26-40-1637-trial013/0",
      "tf_dir": "logs/tuning/ucl/2026-04-01_19-26-40-1637/runs/ucl_bresnet/tuning_sweep_CIL_tune_013_beta-2em04_lr-1em04-2026-04-01_19-26-40-1637-trial013/0/tfdir",
      "params": {
        "beta": 0.0002,
        "lr": 0.0001
      },
      "trial_params": {
        "beta": 0.0002,
        "lr": 0.0001
      },
      "fixed_params": {},
      "val_per_task": [
        0.35759371519088745,
        0.09191450476646423,
        0.0
      ],
      "val_mean": 0.14983607331911722,
      "val_f1_mean": 0.06846633260957984,
      "val_det_per_task": [
        0.5,
        0.5,
        0.5
      ],
      "val_det_mean": 0.5,
      "val_pfa_per_task": [
        1.0,
        1.0,
        1.0
      ],
      "val_pfa_mean": 1.0,
      "test_per_task": [],
      "test_mean": NaN,
      "test_det_per_task": [],
      "test_det_mean": NaN,
      "test_pfa_per_task": [],
      "test_pfa_mean": NaN,
      "score": 0.06846633260957984,
      "duration_sec": 93.9225480556488
    },
    {
      "status": "ok",
      "trial": 14,
      "log_dir": "logs/tuning/ucl/2026-04-01_19-26-40-1637/runs/ucl_bresnet/tuning_sweep_CIL_tune_014_beta-2em04_lr-3em05-2026-04-01_19-26-40-1637-trial014/0",
      "tf_dir": "logs/tuning/ucl/2026-04-01_19-26-40-1637/runs/ucl_bresnet/tuning_sweep_CIL_tune_014_beta-2em04_lr-3em05-2026-04-01_19-26-40-1637-trial014/0/tfdir",
      "params": {
        "beta": 0.0002,
        "lr": 3e-05
      },
      "trial_params": {
        "beta": 0.0002,
        "lr": 3e-05
      },
      "fixed_params": {},
      "val_per_task": [
        0.2909252345561981,
        0.09698937088251114,
        0.0
      ],
      "val_mean": 0.12930486847956976,
      "val_f1_mean": 0.060964251402102904,
      "val_det_per_task": [
        0.5,
        0.5,
        0.5
      ],
      "val_det_mean": 0.5,
      "val_pfa_per_task": [
        1.0,
        1.0,
        1.0
      ],
      "val_pfa_mean": 1.0,
      "test_per_task": [],
      "test_mean": NaN,
      "test_det_per_task": [],
      "test_det_mean": NaN,
      "test_pfa_per_task": [],
      "test_pfa_mean": NaN,
      "score": 0.060964251402102904,
      "duration_sec": 92.91007781028748
    },
    {
      "status": "ok",
      "trial": 15,
      "log_dir": "logs/tuning/ucl/2026-04-01_19-26-40-1637/runs/ucl_bresnet/tuning_sweep_CIL_tune_015_beta-2em04_lr-1em05-2026-04-01_19-26-40-1637-trial015/0",
      "tf_dir": "logs/tuning/ucl/2026-04-01_19-26-40-1637/runs/ucl_bresnet/tuning_sweep_CIL_tune_015_beta-2em04_lr-1em05-2026-04-01_19-26-40-1637-trial015/0/tfdir",
      "params": {
        "beta": 0.0002,
        "lr": 1e-05
      },
      "trial_params": {
        "beta": 0.0002,
        "lr": 1e-05
      },
      "fixed_params": {},
      "val_per_task": [
        0.2944965958595276,
        0.09646464884281158,
        0.0
      ],
      "val_mean": 0.13032041490077972,
      "val_f1_mean": 0.054436236854371406,
      "val_det_per_task": [
        0.5,
        0.5,
        0.5
      ],
      "val_det_mean": 0.5,
      "val_pfa_per_task": [
        1.0,
        1.0,
        1.0
      ],
      "val_pfa_mean": 1.0,
      "test_per_task": [],
      "test_mean": NaN,
      "test_det_per_task": [],
      "test_det_mean": NaN,
      "test_pfa_per_task": [],
      "test_pfa_mean": NaN,
      "score": 0.054436236854371406,
      "duration_sec": 91.98113822937012
    },
    {
      "status": "ok",
      "trial": 16,
      "log_dir": "logs/tuning/ucl/2026-04-01_19-26-40-1637/runs/ucl_bresnet/tuning_sweep_CIL_tune_016_beta-1em03_lr-3em02-2026-04-01_19-26-40-1637-trial016/0",
      "tf_dir": "logs/tuning/ucl/2026-04-01_19-26-40-1637/runs/ucl_bresnet/tuning_sweep_CIL_tune_016_beta-1em03_lr-3em02-2026-04-01_19-26-40-1637-trial016/0/tfdir",
      "params": {
        "beta": 0.001,
        "lr": 0.03
      },
      "trial_params": {
        "beta": 0.001,
        "lr": 0.03
      },
      "fixed_params": {},
      "val_per_task": [
        0.2527916431427002,
        0.0492057241499424,
        0.0
      ],
      "val_mean": 0.10066578909754753,
      "val_f1_mean": 0.04179141764014401,
      "val_det_per_task": [
        0.5,
        0.5,
        0.5
      ],
      "val_det_mean": 0.5,
      "val_pfa_per_task": [
        1.0,
        1.0,
        1.0
      ],
      "val_pfa_mean": 1.0,
      "test_per_task": [],
      "test_mean": NaN,
      "test_det_per_task": [],
      "test_det_mean": NaN,
      "test_pfa_per_task": [],
      "test_pfa_mean": NaN,
      "score": 0.04179141764014401,
      "duration_sec": 93.5972330570221
    },
    {
      "status": "ok",
      "trial": 17,
      "log_dir": "logs/tuning/ucl/2026-04-01_19-26-40-1637/runs/ucl_bresnet/tuning_sweep_CIL_tune_017_beta-1em03_lr-1em02-2026-04-01_19-26-40-1637-trial017/0",
      "tf_dir": "logs/tuning/ucl/2026-04-01_19-26-40-1637/runs/ucl_bresnet/tuning_sweep_CIL_tune_017_beta-1em03_lr-1em02-2026-04-01_19-26-40-1637-trial017/0/tfdir",
      "params": {
        "beta": 0.001,
        "lr": 0.01
      },
      "trial_params": {
        "beta": 0.001,
        "lr": 0.01
      },
      "fixed_params": {},
      "val_per_task": [
        0.341159850358963,
        0.11985285580158234,
        0.0
      ],
      "val_mean": 0.1536709020535151,
      "val_f1_mean": 0.07435038284548558,
      "val_det_per_task": [
        0.5,
        0.5,
        0.5
      ],
      "val_det_mean": 0.5,
      "val_pfa_per_task": [
        1.0,
        1.0,
        1.0
      ],
      "val_pfa_mean": 1.0,
      "test_per_task": [],
      "test_mean": NaN,
      "test_det_per_task": [],
      "test_det_mean": NaN,
      "test_pfa_per_task": [],
      "test_pfa_mean": NaN,
      "score": 0.07435038284548558,
      "duration_sec": 92.4802348613739
    },
    {
      "status": "ok",
      "trial": 18,
      "log_dir": "logs/tuning/ucl/2026-04-01_19-26-40-1637/runs/ucl_bresnet/tuning_sweep_CIL_tune_018_beta-1em03_lr-3em03-2026-04-01_19-26-40-1637-trial018/0",
      "tf_dir": "logs/tuning/ucl/2026-04-01_19-26-40-1637/runs/ucl_bresnet/tuning_sweep_CIL_tune_018_beta-1em03_lr-3em03-2026-04-01_19-26-40-1637-trial018/0/tfdir",
      "params": {
        "beta": 0.001,
        "lr": 0.003
      },
      "trial_params": {
        "beta": 0.001,
        "lr": 0.003
      },
      "fixed_params": {},
      "val_per_task": [
        0.2800600528717041,
        0.09646464884281158,
        0.0
      ],
      "val_mean": 0.12550823390483856,
      "val_f1_mean": 0.043650606805706114,
      "val_det_per_task": [
        0.5,
        0.5,
        0.5
      ],
      "val_det_mean": 0.5,
      "val_pfa_per_task": [
        1.0,
        1.0,
        1.0
      ],
      "val_pfa_mean": 1.0,
      "test_per_task": [],
      "test_mean": NaN,
      "test_det_per_task": [],
      "test_det_mean": NaN,
      "test_pfa_per_task": [],
      "test_pfa_mean": NaN,
      "score": 0.043650606805706114,
      "duration_sec": 91.45655822753906
    },
    {
      "status": "ok",
      "trial": 19,
      "log_dir": "logs/tuning/ucl/2026-04-01_19-26-40-1637/runs/ucl_bresnet/tuning_sweep_CIL_tune_019_beta-1em03_lr-1em03-2026-04-01_19-26-40-1637-trial019/0",
      "tf_dir": "logs/tuning/ucl/2026-04-01_19-26-40-1637/runs/ucl_bresnet/tuning_sweep_CIL_tune_019_beta-1em03_lr-1em03-2026-04-01_19-26-40-1637-trial019/0/tfdir",
      "params": {
        "beta": 0.001,
        "lr": 0.001
      },
      "trial_params": {
        "beta": 0.001,
        "lr": 0.001
      },
      "fixed_params": {},
      "val_per_task": [
        0.3214416205883026,
        0.09722541272640228,
        0.0
      ],
      "val_mean": 0.1395556777715683,
      "val_f1_mean": 0.06988044827976808,
      "val_det_per_task": [
        0.5,
        0.5,
        0.5
      ],
      "val_det_mean": 0.5,
      "val_pfa_per_task": [
        1.0,
        1.0,
        1.0
      ],
      "val_pfa_mean": 1.0,
      "test_per_task": [],
      "test_mean": NaN,
      "test_det_per_task": [],
      "test_det_mean": NaN,
      "test_pfa_per_task": [],
      "test_pfa_mean": NaN,
      "score": 0.06988044827976808,
      "duration_sec": 92.28300094604492
    },
    {
      "status": "ok",
      "trial": 20,
      "log_dir": "logs/tuning/ucl/2026-04-01_19-26-40-1637/runs/ucl_bresnet/tuning_sweep_CIL_tune_020_beta-1em03_lr-3em04-2026-04-01_19-26-40-1637-trial020/0",
      "tf_dir": "logs/tuning/ucl/2026-04-01_19-26-40-1637/runs/ucl_bresnet/tuning_sweep_CIL_tune_020_beta-1em03_lr-3em04-2026-04-01_19-26-40-1637-trial020/0/tfdir",
      "params": {
        "beta": 0.001,
        "lr": 0.0003
      },
      "trial_params": {
        "beta": 0.001,
        "lr": 0.0003
      },
      "fixed_params": {},
      "val_per_task": [
        0.34326523542404175,
        0.09754588454961777,
        0.0
      ],
      "val_mean": 0.14693703999121985,
      "val_f1_mean": 0.04365773132787248,
      "val_det_per_task": [
        0.5,
        0.5,
        0.5
      ],
      "val_det_mean": 0.5,
      "val_pfa_per_task": [
        1.0,
        1.0,
        1.0
      ],
      "val_pfa_mean": 1.0,
      "test_per_task": [],
      "test_mean": NaN,
      "test_det_per_task": [],
      "test_det_mean": NaN,
      "test_pfa_per_task": [],
      "test_pfa_mean": NaN,
      "score": 0.04365773132787248,
      "duration_sec": 91.74088907241821
    },
    {
      "status": "ok",
      "trial": 21,
      "log_dir": "logs/tuning/ucl/2026-04-01_19-26-40-1637/runs/ucl_bresnet/tuning_sweep_CIL_tune_021_beta-1em03_lr-1em04-2026-04-01_19-26-40-1637-trial021/0",
      "tf_dir": "logs/tuning/ucl/2026-04-01_19-26-40-1637/runs/ucl_bresnet/tuning_sweep_CIL_tune_021_beta-1em03_lr-1em04-2026-04-01_19-26-40-1637-trial021/0/tfdir",
      "params": {
        "beta": 0.001,
        "lr": 0.0001
      },
      "trial_params": {
        "beta": 0.001,
        "lr": 0.0001
      },
      "fixed_params": {},
      "val_per_task": [
        0.3550322949886322,
        0.08977295458316803,
        0.0
      ],
      "val_mean": 0.1482684165239334,
      "val_f1_mean": 0.05026336387738143,
      "val_det_per_task": [
        0.5,
        0.5,
        0.5
      ],
      "val_det_mean": 0.5,
      "val_pfa_per_task": [
        1.0,
        1.0,
        1.0
      ],
      "val_pfa_mean": 1.0,
      "test_per_task": [],
      "test_mean": NaN,
      "test_det_per_task": [],
      "test_det_mean": NaN,
      "test_pfa_per_task": [],
      "test_pfa_mean": NaN,
      "score": 0.05026336387738143,
      "duration_sec": 93.22328042984009
    },
    {
      "status": "ok",
      "trial": 22,
      "log_dir": "logs/tuning/ucl/2026-04-01_19-26-40-1637/runs/ucl_bresnet/tuning_sweep_CIL_tune_022_beta-1em03_lr-3em05-2026-04-01_19-26-40-1637-trial022/0",
      "tf_dir": "logs/tuning/ucl/2026-04-01_19-26-40-1637/runs/ucl_bresnet/tuning_sweep_CIL_tune_022_beta-1em03_lr-3em05-2026-04-01_19-26-40-1637-trial022/0/tfdir",
      "params": {
        "beta": 0.001,
        "lr": 3e-05
      },
      "trial_params": {
        "beta": 0.001,
        "lr": 3e-05
      },
      "fixed_params": {},
      "val_per_task": [
        0.31768715381622314,
        0.096694216132164,
        0.0
      ],
      "val_mean": 0.13812712331612906,
      "val_f1_mean": 0.06463768211704378,
      "val_det_per_task": [
        0.5,
        0.5,
        0.5
      ],
      "val_det_mean": 0.5,
      "val_pfa_per_task": [
        1.0,
        1.0,
        1.0
      ],
      "val_pfa_mean": 1.0,
      "test_per_task": [],
      "test_mean": NaN,
      "test_det_per_task": [],
      "test_det_mean": NaN,
      "test_pfa_per_task": [],
      "test_pfa_mean": NaN,
      "score": 0.06463768211704378,
      "duration_sec": 92.99260520935059
    },
    {
      "status": "ok",
      "trial": 23,
      "log_dir": "logs/tuning/ucl/2026-04-01_19-26-40-1637/runs/ucl_bresnet/tuning_sweep_CIL_tune_023_beta-1em03_lr-1em05-2026-04-01_19-26-40-1637-trial023/0",
      "tf_dir": "logs/tuning/ucl/2026-04-01_19-26-40-1637/runs/ucl_bresnet/tuning_sweep_CIL_tune_023_beta-1em03_lr-1em05-2026-04-01_19-26-40-1637-trial023/0/tfdir",
      "params": {
        "beta": 0.001,
        "lr": 1e-05
      },
      "trial_params": {
        "beta": 0.001,
        "lr": 1e-05
      },
      "fixed_params": {},
      "val_per_task": [
        0.29481032490730286,
        0.09646464884281158,
        0.0
      ],
      "val_mean": 0.13042499125003815,
      "val_f1_mean": 0.05489175446089702,
      "val_det_per_task": [
        0.5,
        0.5,
        0.5
      ],
      "val_det_mean": 0.5,
      "val_pfa_per_task": [
        1.0,
        1.0,
        1.0
      ],
      "val_pfa_mean": 1.0,
      "test_per_task": [],
      "test_mean": NaN,
      "test_det_per_task": [],
      "test_det_mean": NaN,
      "test_pfa_per_task": [],
      "test_pfa_mean": NaN,
      "score": 0.05489175446089702,
      "duration_sec": 92.2650773525238
    },
    {
      "status": "ok",
      "trial": 24,
      "log_dir": "logs/tuning/ucl/2026-04-01_19-26-40-1637/runs/ucl_bresnet/tuning_sweep_CIL_tune_024_beta-2em03_lr-3em02-2026-04-01_19-26-40-1637-trial024/0",
      "tf_dir": "logs/tuning/ucl/2026-04-01_19-26-40-1637/runs/ucl_bresnet/tuning_sweep_CIL_tune_024_beta-2em03_lr-3em02-2026-04-01_19-26-40-1637-trial024/0/tfdir",
      "params": {
        "beta": 0.002,
        "lr": 0.03
      },
      "trial_params": {
        "beta": 0.002,
        "lr": 0.03
      },
      "fixed_params": {},
      "val_per_task": [
        0.2721620500087738,
        0.0063670361414551735,
        0.0
      ],
      "val_mean": 0.09284302871674299,
      "val_f1_mean": 0.04111758723604641,
      "val_det_per_task": [
        0.5,
        0.5,
        0.5
      ],
      "val_det_mean": 0.5,
      "val_pfa_per_task": [
        1.0,
        1.0,
        1.0
      ],
      "val_pfa_mean": 1.0,
      "test_per_task": [],
      "test_mean": NaN,
      "test_det_per_task": [],
      "test_det_mean": NaN,
      "test_pfa_per_task": [],
      "test_pfa_mean": NaN,
      "score": 0.04111758723604641,
      "duration_sec": 93.76845932006836
    },
    {
      "status": "ok",
      "trial": 25,
      "log_dir": "logs/tuning/ucl/2026-04-01_19-26-40-1637/runs/ucl_bresnet/tuning_sweep_CIL_tune_025_beta-2em03_lr-1em02-2026-04-01_19-26-40-1637-trial025/0",
      "tf_dir": "logs/tuning/ucl/2026-04-01_19-26-40-1637/runs/ucl_bresnet/tuning_sweep_CIL_tune_025_beta-2em03_lr-1em02-2026-04-01_19-26-40-1637-trial025/0/tfdir",
      "params": {
        "beta": 0.002,
        "lr": 0.01
      },
      "trial_params": {
        "beta": 0.002,
        "lr": 0.01
      },
      "fixed_params": {},
      "val_per_task": [
        0.35187897086143494,
        0.07788177579641342,
        0.0
      ],
      "val_mean": 0.14325358221928278,
      "val_f1_mean": 0.05423024135703953,
      "val_det_per_task": [
        0.5,
        0.5,
        0.5
      ],
      "val_det_mean": 0.5,
      "val_pfa_per_task": [
        1.0,
        1.0,
        1.0
      ],
      "val_pfa_mean": 1.0,
      "test_per_task": [],
      "test_mean": NaN,
      "test_det_per_task": [],
      "test_det_mean": NaN,
      "test_pfa_per_task": [],
      "test_pfa_mean": NaN,
      "score": 0.05423024135703953,
      "duration_sec": 93.04200673103333
    },
    {
      "status": "ok",
      "trial": 26,
      "log_dir": "logs/tuning/ucl/2026-04-01_19-26-40-1637/runs/ucl_bresnet/tuning_sweep_CIL_tune_026_beta-2em03_lr-3em03-2026-04-01_19-26-40-1637-trial026/0",
      "tf_dir": "logs/tuning/ucl/2026-04-01_19-26-40-1637/runs/ucl_bresnet/tuning_sweep_CIL_tune_026_beta-2em03_lr-3em03-2026-04-01_19-26-40-1637-trial026/0/tfdir",
      "params": {
        "beta": 0.002,
        "lr": 0.003
      },
      "trial_params": {
        "beta": 0.002,
        "lr": 0.003
      },
      "fixed_params": {},
      "val_per_task": [
        0.2841256558895111,
        0.09646464884281158,
        0.0
      ],
      "val_mean": 0.12686343491077423,
      "val_f1_mean": 0.050272886735887444,
      "val_det_per_task": [
        0.5,
        0.5,
        0.5
      ],
      "val_det_mean": 0.5,
      "val_pfa_per_task": [
        1.0,
        1.0,
        1.0
      ],
      "val_pfa_mean": 1.0,
      "test_per_task": [],
      "test_mean": NaN,
      "test_det_per_task": [],
      "test_det_mean": NaN,
      "test_pfa_per_task": [],
      "test_pfa_mean": NaN,
      "score": 0.050272886735887444,
      "duration_sec": 92.35883259773254
    },
    {
      "status": "ok",
      "trial": 27,
      "log_dir": "logs/tuning/ucl/2026-04-01_19-26-40-1637/runs/ucl_bresnet/tuning_sweep_CIL_tune_027_beta-2em03_lr-1em03-2026-04-01_19-26-40-1637-trial027/0",
      "tf_dir": "logs/tuning/ucl/2026-04-01_19-26-40-1637/runs/ucl_bresnet/tuning_sweep_CIL_tune_027_beta-2em03_lr-1em03-2026-04-01_19-26-40-1637-trial027/0/tfdir",
      "params": {
        "beta": 0.002,
        "lr": 0.001
      },
      "trial_params": {
        "beta": 0.002,
        "lr": 0.001
      },
      "fixed_params": {},
      "val_per_task": [
        0.3378101885318756,
        0.10301343351602554,
        0.0
      ],
      "val_mean": 0.14694120734930038,
      "val_f1_mean": 0.0738370467641379,
      "val_det_per_task": [
        0.5,
        0.5,
        0.5
      ],
      "val_det_mean": 0.5,
      "val_pfa_per_task": [
        1.0,
        1.0,
        1.0
      ],
      "val_pfa_mean": 1.0,
      "test_per_task": [],
      "test_mean": NaN,
      "test_det_per_task": [],
      "test_det_mean": NaN,
      "test_pfa_per_task": [],
      "test_pfa_mean": NaN,
      "score": 0.0738370467641379,
      "duration_sec": 94.13564825057983
    },
    {
      "status": "ok",
      "trial": 28,
      "log_dir": "logs/tuning/ucl/2026-04-01_19-26-40-1637/runs/ucl_bresnet/tuning_sweep_CIL_tune_028_beta-2em03_lr-3em04-2026-04-01_19-26-40-1637-trial028/0",
      "tf_dir": "logs/tuning/ucl/2026-04-01_19-26-40-1637/runs/ucl_bresnet/tuning_sweep_CIL_tune_028_beta-2em03_lr-3em04-2026-04-01_19-26-40-1637-trial028/0/tfdir",
      "params": {
        "beta": 0.002,
        "lr": 0.0003
      },
      "trial_params": {
        "beta": 0.002,
        "lr": 0.0003
      },
      "fixed_params": {},
      "val_per_task": [
        0.3469647467136383,
        0.023612499237060547,
        0.0
      ],
      "val_mean": 0.12352574865023296,
      "val_f1_mean": 0.04000924572664797,
      "val_det_per_task": [
        0.5,
        0.5,
        0.5
      ],
      "val_det_mean": 0.5,
      "val_pfa_per_task": [
        1.0,
        1.0,
        1.0
      ],
      "val_pfa_mean": 1.0,
      "test_per_task": [],
      "test_mean": NaN,
      "test_det_per_task": [],
      "test_det_mean": NaN,
      "test_pfa_per_task": [],
      "test_pfa_mean": NaN,
      "score": 0.04000924572664797,
      "duration_sec": 92.10267806053162
    },
    {
      "status": "ok",
      "trial": 29,
      "log_dir": "logs/tuning/ucl/2026-04-01_19-26-40-1637/runs/ucl_bresnet/tuning_sweep_CIL_tune_029_beta-2em03_lr-1em04-2026-04-01_19-26-40-1637-trial029/0",
      "tf_dir": "logs/tuning/ucl/2026-04-01_19-26-40-1637/runs/ucl_bresnet/tuning_sweep_CIL_tune_029_beta-2em03_lr-1em04-2026-04-01_19-26-40-1637-trial029/0/tfdir",
      "params": {
        "beta": 0.002,
        "lr": 0.0001
      },
      "trial_params": {
        "beta": 0.002,
        "lr": 0.0001
      },
      "fixed_params": {},
      "val_per_task": [
        0.3550322949886322,
        0.09042230993509293,
        0.0
      ],
      "val_mean": 0.14848486830790839,
      "val_f1_mean": 0.0503160272693166,
      "val_det_per_task": [
        0.5,
        0.5,
        0.5
      ],
      "val_det_mean": 0.5,
      "val_pfa_per_task": [
        1.0,
        1.0,
        1.0
      ],
      "val_pfa_mean": 1.0,
      "test_per_task": [],
      "test_mean": NaN,
      "test_det_per_task": [],
      "test_det_mean": NaN,
      "test_pfa_per_task": [],
      "test_pfa_mean": NaN,
      "score": 0.0503160272693166,
      "duration_sec": 91.26211476325989
    },
    {
      "status": "ok",
      "trial": 30,
      "log_dir": "logs/tuning/ucl/2026-04-01_19-26-40-1637/runs/ucl_bresnet/tuning_sweep_CIL_tune_030_beta-2em03_lr-3em05-2026-04-01_19-26-40-1637-trial030/0",
      "tf_dir": "logs/tuning/ucl/2026-04-01_19-26-40-1637/runs/ucl_bresnet/tuning_sweep_CIL_tune_030_beta-2em03_lr-3em05-2026-04-01_19-26-40-1637-trial030/0/tfdir",
      "params": {
        "beta": 0.002,
        "lr": 3e-05
      },
      "trial_params": {
        "beta": 0.002,
        "lr": 3e-05
      },
      "fixed_params": {},
      "val_per_task": [
        0.30263951420783997,
        0.09698937088251114,
        0.0
      ],
      "val_mean": 0.13320962836345038,
      "val_f1_mean": 0.062166361889047554,
      "val_det_per_task": [
        0.5,
        0.5,
        0.5
      ],
      "val_det_mean": 0.5,
      "val_pfa_per_task": [
        1.0,
        1.0,
        1.0
      ],
      "val_pfa_mean": 1.0,
      "test_per_task": [],
      "test_mean": NaN,
      "test_det_per_task": [],
      "test_det_mean": NaN,
      "test_pfa_per_task": [],
      "test_pfa_mean": NaN,
      "score": 0.062166361889047554,
      "duration_sec": 93.72454690933228
    },
    {
      "status": "ok",
      "trial": 31,
      "log_dir": "logs/tuning/ucl/2026-04-01_19-26-40-1637/runs/ucl_bresnet/tuning_sweep_CIL_tune_031_beta-2em03_lr-1em05-2026-04-01_19-26-40-1637-trial031/0",
      "tf_dir": "logs/tuning/ucl/2026-04-01_19-26-40-1637/runs/ucl_bresnet/tuning_sweep_CIL_tune_031_beta-2em03_lr-1em05-2026-04-01_19-26-40-1637-trial031/0/tfdir",
      "params": {
        "beta": 0.002,
        "lr": 1e-05
      },
      "trial_params": {
        "beta": 0.002,
        "lr": 1e-05
      },
      "fixed_params": {},
      "val_per_task": [
        0.29970669746398926,
        0.09646464884281158,
        0.0
      ],
      "val_mean": 0.13205711543560028,
      "val_f1_mean": 0.05506190451973888,
      "val_det_per_task": [
        0.5,
        0.5,
        0.5
      ],
      "val_det_mean": 0.5,
      "val_pfa_per_task": [
        1.0,
        1.0,
        1.0
      ],
      "val_pfa_mean": 1.0,
      "test_per_task": [],
      "test_mean": NaN,
      "test_det_per_task": [],
      "test_det_mean": NaN,
      "test_pfa_per_task": [],
      "test_pfa_mean": NaN,
      "score": 0.05506190451973888,
      "duration_sec": 92.1232397556305
    },
    {
      "status": "ok",
      "trial": 32,
      "log_dir": "logs/tuning/ucl/2026-04-01_19-26-40-1637/runs/ucl_bresnet/tuning_sweep_CIL_tune_032_beta-1em02_lr-3em02-2026-04-01_19-26-40-1637-trial032/0",
      "tf_dir": "logs/tuning/ucl/2026-04-01_19-26-40-1637/runs/ucl_bresnet/tuning_sweep_CIL_tune_032_beta-1em02_lr-3em02-2026-04-01_19-26-40-1637-trial032/0/tfdir",
      "params": {
        "beta": 0.01,
        "lr": 0.03
      },
      "trial_params": {
        "beta": 0.01,
        "lr": 0.03
      },
      "fixed_params": {},
      "val_per_task": [
        0.1771106719970703,
        0.00025252526393160224,
        0.0
      ],
      "val_mean": 0.0591210657536673,
      "val_f1_mean": 0.019971414274005988,
      "val_det_per_task": [
        0.5,
        0.5,
        0.5
      ],
      "val_det_mean": 0.5,
      "val_pfa_per_task": [
        1.0,
        1.0,
        1.0
      ],
      "val_pfa_mean": 1.0,
      "test_per_task": [],
      "test_mean": NaN,
      "test_det_per_task": [],
      "test_det_mean": NaN,
      "test_pfa_per_task": [],
      "test_pfa_mean": NaN,
      "score": 0.019971414274005988,
      "duration_sec": 91.7590823173523
    },
    {
      "status": "ok",
      "trial": 33,
      "log_dir": "logs/tuning/ucl/2026-04-01_19-26-40-1637/runs/ucl_bresnet/tuning_sweep_CIL_tune_033_beta-1em02_lr-1em02-2026-04-01_19-26-40-1637-trial033/0",
      "tf_dir": "logs/tuning/ucl/2026-04-01_19-26-40-1637/runs/ucl_bresnet/tuning_sweep_CIL_tune_033_beta-1em02_lr-1em02-2026-04-01_19-26-40-1637-trial033/0/tfdir",
      "params": {
        "beta": 0.01,
        "lr": 0.01
      },
      "trial_params": {
        "beta": 0.01,
        "lr": 0.01
      },
      "fixed_params": {},
      "val_per_task": [
        0.36317411065101624,
        0.09646137058734894,
        0.0
      ],
      "val_mean": 0.15321182707945505,
      "val_f1_mean": 0.07112969999884801,
      "val_det_per_task": [
        0.5,
        0.5,
        0.5
      ],
      "val_det_mean": 0.5,
      "val_pfa_per_task": [
        1.0,
        1.0,
        1.0
      ],
      "val_pfa_mean": 1.0,
      "test_per_task": [],
      "test_mean": NaN,
      "test_det_per_task": [],
      "test_det_mean": NaN,
      "test_pfa_per_task": [],
      "test_pfa_mean": NaN,
      "score": 0.07112969999884801,
      "duration_sec": 93.81950426101685
    },
    {
      "status": "ok",
      "trial": 34,
      "log_dir": "logs/tuning/ucl/2026-04-01_19-26-40-1637/runs/ucl_bresnet/tuning_sweep_CIL_tune_034_beta-1em02_lr-3em03-2026-04-01_19-26-40-1637-trial034/0",
      "tf_dir": "logs/tuning/ucl/2026-04-01_19-26-40-1637/runs/ucl_bresnet/tuning_sweep_CIL_tune_034_beta-1em02_lr-3em03-2026-04-01_19-26-40-1637-trial034/0/tfdir",
      "params": {
        "beta": 0.01,
        "lr": 0.003
      },
      "trial_params": {
        "beta": 0.01,
        "lr": 0.003
      },
      "fixed_params": {},
      "val_per_task": [
        0.26515647768974304,
        0.09646464884281158,
        0.0
      ],
      "val_mean": 0.12054037551085155,
      "val_f1_mean": 0.04446171414370397,
      "val_det_per_task": [
        0.5,
        0.5,
        0.5
      ],
      "val_det_mean": 0.5,
      "val_pfa_per_task": [
        1.0,
        1.0,
        1.0
      ],
      "val_pfa_mean": 1.0,
      "test_per_task": [],
      "test_mean": NaN,
      "test_det_per_task": [],
      "test_det_mean": NaN,
      "test_pfa_per_task": [],
      "test_pfa_mean": NaN,
      "score": 0.04446171414370397,
      "duration_sec": 93.2360429763794
    },
    {
      "status": "ok",
      "trial": 35,
      "log_dir": "logs/tuning/ucl/2026-04-01_19-26-40-1637/runs/ucl_bresnet/tuning_sweep_CIL_tune_035_beta-1em02_lr-1em03-2026-04-01_19-26-40-1637-trial035/0",
      "tf_dir": "logs/tuning/ucl/2026-04-01_19-26-40-1637/runs/ucl_bresnet/tuning_sweep_CIL_tune_035_beta-1em02_lr-1em03-2026-04-01_19-26-40-1637-trial035/0/tfdir",
      "params": {
        "beta": 0.01,
        "lr": 0.001
      },
      "trial_params": {
        "beta": 0.01,
        "lr": 0.001
      },
      "fixed_params": {},
      "val_per_task": [
        0.3129065930843353,
        0.09878513216972351,
        0.0
      ],
      "val_mean": 0.13723057508468628,
      "val_f1_mean": 0.06678305611339062,
      "val_det_per_task": [
        0.5,
        0.5,
        0.5
      ],
      "val_det_mean": 0.5,
      "val_pfa_per_task": [
        1.0,
        1.0,
        1.0
      ],
      "val_pfa_mean": 1.0,
      "test_per_task": [],
      "test_mean": NaN,
      "test_det_per_task": [],
      "test_det_mean": NaN,
      "test_pfa_per_task": [],
      "test_pfa_mean": NaN,
      "score": 0.06678305611339062,
      "duration_sec": 91.36972665786743
    },
    {
      "status": "ok",
      "trial": 36,
      "log_dir": "logs/tuning/ucl/2026-04-01_19-26-40-1637/runs/ucl_bresnet/tuning_sweep_CIL_tune_036_beta-1em02_lr-3em04-2026-04-01_19-26-40-1637-trial036/0",
      "tf_dir": "logs/tuning/ucl/2026-04-01_19-26-40-1637/runs/ucl_bresnet/tuning_sweep_CIL_tune_036_beta-1em02_lr-3em04-2026-04-01_19-26-40-1637-trial036/0/tfdir",
      "params": {
        "beta": 0.01,
        "lr": 0.0003
      },
      "trial_params": {
        "beta": 0.01,
        "lr": 0.0003
      },
      "fixed_params": {},
      "val_per_task": [
        0.3304296135902405,
        0.09234079718589783,
        0.0
      ],
      "val_mean": 0.14092347025871277,
      "val_f1_mean": 0.04298673282238355,
      "val_det_per_task": [
        0.5,
        0.5,
        0.5
      ],
      "val_det_mean": 0.5,
      "val_pfa_per_task": [
        1.0,
        1.0,
        1.0
      ],
      "val_pfa_mean": 1.0,
      "test_per_task": [],
      "test_mean": NaN,
      "test_det_per_task": [],
      "test_det_mean": NaN,
      "test_pfa_per_task": [],
      "test_pfa_mean": NaN,
      "score": 0.04298673282238355,
      "duration_sec": 92.29423379898071
    },
    {
      "status": "ok",
      "trial": 37,
      "log_dir": "logs/tuning/ucl/2026-04-01_19-26-40-1637/runs/ucl_bresnet/tuning_sweep_CIL_tune_037_beta-1em02_lr-1em04-2026-04-01_19-26-40-1637-trial037/0",
      "tf_dir": "logs/tuning/ucl/2026-04-01_19-26-40-1637/runs/ucl_bresnet/tuning_sweep_CIL_tune_037_beta-1em02_lr-1em04-2026-04-01_19-26-40-1637-trial037/0/tfdir",
      "params": {
        "beta": 0.01,
        "lr": 0.0001
      },
      "trial_params": {
        "beta": 0.01,
        "lr": 0.0001
      },
      "fixed_params": {},
      "val_per_task": [
        0.3550322949886322,
        0.09191450476646423,
        0.0
      ],
      "val_mean": 0.14898226658503214,
      "val_f1_mean": 0.05045740274940173,
      "val_det_per_task": [
        0.5,
        0.5,
        0.5
      ],
      "val_det_mean": 0.5,
      "val_pfa_per_task": [
        1.0,
        1.0,
        1.0
      ],
      "val_pfa_mean": 1.0,
      "test_per_task": [],
      "test_mean": NaN,
      "test_det_per_task": [],
      "test_det_mean": NaN,
      "test_pfa_per_task": [],
      "test_pfa_mean": NaN,
      "score": 0.05045740274940173,
      "duration_sec": 93.14476084709167
    },
    {
      "status": "ok",
      "trial": 38,
      "log_dir": "logs/tuning/ucl/2026-04-01_19-26-40-1637/runs/ucl_bresnet/tuning_sweep_CIL_tune_038_beta-1em02_lr-3em05-2026-04-01_19-26-40-1637-trial038/0",
      "tf_dir": "logs/tuning/ucl/2026-04-01_19-26-40-1637/runs/ucl_bresnet/tuning_sweep_CIL_tune_038_beta-1em02_lr-3em05-2026-04-01_19-26-40-1637-trial038/0/tfdir",
      "params": {
        "beta": 0.01,
        "lr": 3e-05
      },
      "trial_params": {
        "beta": 0.01,
        "lr": 3e-05
      },
      "fixed_params": {},
      "val_per_task": [
        0.3086395263671875,
        0.09698937088251114,
        0.0
      ],
      "val_mean": 0.13520963241656622,
      "val_f1_mean": 0.06370292241027631,
      "val_det_per_task": [
        0.5,
        0.5,
        0.5
      ],
      "val_det_mean": 0.5,
      "val_pfa_per_task": [
        1.0,
        1.0,
        1.0
      ],
      "val_pfa_mean": 1.0,
      "test_per_task": [],
      "test_mean": NaN,
      "test_det_per_task": [],
      "test_det_mean": NaN,
      "test_pfa_per_task": [],
      "test_pfa_mean": NaN,
      "score": 0.06370292241027631,
      "duration_sec": 92.51547694206238
    },
    {
      "status": "ok",
      "trial": 39,
      "log_dir": "logs/tuning/ucl/2026-04-01_19-26-40-1637/runs/ucl_bresnet/tuning_sweep_CIL_tune_039_beta-1em02_lr-1em05-2026-04-01_19-26-40-1637-trial039/0",
      "tf_dir": "logs/tuning/ucl/2026-04-01_19-26-40-1637/runs/ucl_bresnet/tuning_sweep_CIL_tune_039_beta-1em02_lr-1em05-2026-04-01_19-26-40-1637-trial039/0/tfdir",
      "params": {
        "beta": 0.01,
        "lr": 1e-05
      },
      "trial_params": {
        "beta": 0.01,
        "lr": 1e-05
      },
      "fixed_params": {},
      "val_per_task": [
        0.2995162308216095,
        0.09646464884281158,
        0.0
      ],
      "val_mean": 0.13199362655480704,
      "val_f1_mean": 0.05523322835552283,
      "val_det_per_task": [
        0.5,
        0.5,
        0.5
      ],
      "val_det_mean": 0.5,
      "val_pfa_per_task": [
        1.0,
        1.0,
        1.0
      ],
      "val_pfa_mean": 1.0,
      "test_per_task": [],
      "test_mean": NaN,
      "test_det_per_task": [],
      "test_det_mean": NaN,
      "test_pfa_per_task": [],
      "test_pfa_mean": NaN,
      "score": 0.05523322835552283,
      "duration_sec": 93.3005645275116
    },
    {
      "status": "ok",
      "trial": 40,
      "log_dir": "logs/tuning/ucl/2026-04-01_19-26-40-1637/runs/ucl_bresnet/tuning_sweep_CIL_tune_040_beta-2em02_lr-3em02-2026-04-01_19-26-40-1637-trial040/0",
      "tf_dir": "logs/tuning/ucl/2026-04-01_19-26-40-1637/runs/ucl_bresnet/tuning_sweep_CIL_tune_040_beta-2em02_lr-3em02-2026-04-01_19-26-40-1637-trial040/0/tfdir",
      "params": {
        "beta": 0.02,
        "lr": 0.03
      },
      "trial_params": {
        "beta": 0.02,
        "lr": 0.03
      },
      "fixed_params": {},
      "val_per_task": [
        0.34880751371383667,
        0.05870088189840317,
        0.0
      ],
      "val_mean": 0.1358361318707466,
      "val_f1_mean": 0.06023055332357707,
      "val_det_per_task": [
        0.5,
        0.5,
        0.5
      ],
      "val_det_mean": 0.5,
      "val_pfa_per_task": [
        1.0,
        1.0,
        1.0
      ],
      "val_pfa_mean": 1.0,
      "test_per_task": [],
      "test_mean": NaN,
      "test_det_per_task": [],
      "test_det_mean": NaN,
      "test_pfa_per_task": [],
      "test_pfa_mean": NaN,
      "score": 0.06023055332357707,
      "duration_sec": 92.09304356575012
    },
    {
      "status": "ok",
      "trial": 41,
      "log_dir": "logs/tuning/ucl/2026-04-01_19-26-40-1637/runs/ucl_bresnet/tuning_sweep_CIL_tune_041_beta-2em02_lr-1em02-2026-04-01_19-26-40-1637-trial041/0",
      "tf_dir": "logs/tuning/ucl/2026-04-01_19-26-40-1637/runs/ucl_bresnet/tuning_sweep_CIL_tune_041_beta-2em02_lr-1em02-2026-04-01_19-26-40-1637-trial041/0/tfdir",
      "params": {
        "beta": 0.02,
        "lr": 0.01
      },
      "trial_params": {
        "beta": 0.02,
        "lr": 0.01
      },
      "fixed_params": {},
      "val_per_task": [
        0.3559521436691284,
        0.08149071782827377,
        0.0
      ],
      "val_mean": 0.14581428716580072,
      "val_f1_mean": 0.06549652531417058,
      "val_det_per_task": [
        0.5,
        0.5,
        0.5
      ],
      "val_det_mean": 0.5,
      "val_pfa_per_task": [
        1.0,
        1.0,
        1.0
      ],
      "val_pfa_mean": 1.0,
      "test_per_task": [],
      "test_mean": NaN,
      "test_det_per_task": [],
      "test_det_mean": NaN,
      "test_pfa_per_task": [],
      "test_pfa_mean": NaN,
      "score": 0.06549652531417058,
      "duration_sec": 92.86978363990784
    },
    {
      "status": "ok",
      "trial": 42,
      "log_dir": "logs/tuning/ucl/2026-04-01_19-26-40-1637/runs/ucl_bresnet/tuning_sweep_CIL_tune_042_beta-2em02_lr-3em03-2026-04-01_19-26-40-1637-trial042/0",
      "tf_dir": "logs/tuning/ucl/2026-04-01_19-26-40-1637/runs/ucl_bresnet/tuning_sweep_CIL_tune_042_beta-2em02_lr-3em03-2026-04-01_19-26-40-1637-trial042/0/tfdir",
      "params": {
        "beta": 0.02,
        "lr": 0.003
      },
      "trial_params": {
        "beta": 0.02,
        "lr": 0.003
      },
      "fixed_params": {},
      "val_per_task": [
        0.2796497941017151,
        0.09646464884281158,
        0.0
      ],
      "val_mean": 0.12537148098150888,
      "val_f1_mean": 0.04063641806443904,
      "val_det_per_task": [
        0.5,
        0.5,
        0.5
      ],
      "val_det_mean": 0.5,
      "val_pfa_per_task": [
        1.0,
        1.0,
        1.0
      ],
      "val_pfa_mean": 1.0,
      "test_per_task": [],
      "test_mean": NaN,
      "test_det_per_task": [],
      "test_det_mean": NaN,
      "test_pfa_per_task": [],
      "test_pfa_mean": NaN,
      "score": 0.04063641806443904,
      "duration_sec": 92.17903518676758
    },
    {
      "status": "ok",
      "trial": 43,
      "log_dir": "logs/tuning/ucl/2026-04-01_19-26-40-1637/runs/ucl_bresnet/tuning_sweep_CIL_tune_043_beta-2em02_lr-1em03-2026-04-01_19-26-40-1637-trial043/0",
      "tf_dir": "logs/tuning/ucl/2026-04-01_19-26-40-1637/runs/ucl_bresnet/tuning_sweep_CIL_tune_043_beta-2em02_lr-1em03-2026-04-01_19-26-40-1637-trial043/0/tfdir",
      "params": {
        "beta": 0.02,
        "lr": 0.001
      },
      "trial_params": {
        "beta": 0.02,
        "lr": 0.001
      },
      "fixed_params": {},
      "val_per_task": [
        0.3261639475822449,
        0.10836915671825409,
        0.0
      ],
      "val_mean": 0.14484436810016632,
      "val_f1_mean": 0.07244973257405703,
      "val_det_per_task": [
        0.5,
        0.5,
        0.5
      ],
      "val_det_mean": 0.5,
      "val_pfa_per_task": [
        1.0,
        1.0,
        1.0
      ],
      "val_pfa_mean": 1.0,
      "test_per_task": [],
      "test_mean": NaN,
      "test_det_per_task": [],
      "test_det_mean": NaN,
      "test_pfa_per_task": [],
      "test_pfa_mean": NaN,
      "score": 0.07244973257405703,
      "duration_sec": 91.92665410041809
    },
    {
      "status": "ok",
      "trial": 44,
      "log_dir": "logs/tuning/ucl/2026-04-01_19-26-40-1637/runs/ucl_bresnet/tuning_sweep_CIL_tune_044_beta-2em02_lr-3em04-2026-04-01_19-26-40-1637-trial044/0",
      "tf_dir": "logs/tuning/ucl/2026-04-01_19-26-40-1637/runs/ucl_bresnet/tuning_sweep_CIL_tune_044_beta-2em02_lr-3em04-2026-04-01_19-26-40-1637-trial044/0/tfdir",
      "params": {
        "beta": 0.02,
        "lr": 0.0003
      },
      "trial_params": {
        "beta": 0.02,
        "lr": 0.0003
      },
      "fixed_params": {},
      "val_per_task": [
        0.32235270738601685,
        0.07587909698486328,
        0.0
      ],
      "val_mean": 0.13274393479029337,
      "val_f1_mean": 0.04260429375851654,
      "val_det_per_task": [
        0.5,
        0.5,
        0.5
      ],
      "val_det_mean": 0.5,
      "val_pfa_per_task": [
        1.0,
        1.0,
        1.0
      ],
      "val_pfa_mean": 1.0,
      "test_per_task": [],
      "test_mean": NaN,
      "test_det_per_task": [],
      "test_det_mean": NaN,
      "test_pfa_per_task": [],
      "test_pfa_mean": NaN,
      "score": 0.04260429375851654,
      "duration_sec": 93.82299780845642
    },
    {
      "status": "ok",
      "trial": 45,
      "log_dir": "logs/tuning/ucl/2026-04-01_19-26-40-1637/runs/ucl_bresnet/tuning_sweep_CIL_tune_045_beta-2em02_lr-1em04-2026-04-01_19-26-40-1637-trial045/0",
      "tf_dir": "logs/tuning/ucl/2026-04-01_19-26-40-1637/runs/ucl_bresnet/tuning_sweep_CIL_tune_045_beta-2em02_lr-1em04-2026-04-01_19-26-40-1637-trial045/0/tfdir",
      "params": {
        "beta": 0.02,
        "lr": 0.0001
      },
      "trial_params": {
        "beta": 0.02,
        "lr": 0.0001
      },
      "fixed_params": {},
      "val_per_task": [
        0.352365642786026,
        0.09088144451379776,
        0.0
      ],
      "val_mean": 0.14774902909994125,
      "val_f1_mean": 0.0674830029479735,
      "val_det_per_task": [
        0.5,
        0.5,
        0.5
      ],
      "val_det_mean": 0.5,
      "val_pfa_per_task": [
        1.0,
        1.0,
        1.0
      ],
      "val_pfa_mean": 1.0,
      "test_per_task": [],
      "test_mean": NaN,
      "test_det_per_task": [],
      "test_det_mean": NaN,
      "test_pfa_per_task": [],
      "test_pfa_mean": NaN,
      "score": 0.0674830029479735,
      "duration_sec": 93.43111491203308
    },
    {
      "status": "ok",
      "trial": 46,
      "log_dir": "logs/tuning/ucl/2026-04-01_19-26-40-1637/runs/ucl_bresnet/tuning_sweep_CIL_tune_046_beta-2em02_lr-3em05-2026-04-01_19-26-40-1637-trial046/0",
      "tf_dir": "logs/tuning/ucl/2026-04-01_19-26-40-1637/runs/ucl_bresnet/tuning_sweep_CIL_tune_046_beta-2em02_lr-3em05-2026-04-01_19-26-40-1637-trial046/0/tfdir",
      "params": {
        "beta": 0.02,
        "lr": 3e-05
      },
      "trial_params": {
        "beta": 0.02,
        "lr": 3e-05
      },
      "fixed_params": {},
      "val_per_task": [
        0.3019728660583496,
        0.096694216132164,
        0.0
      ],
      "val_mean": 0.13288902739683786,
      "val_f1_mean": 0.06122503705860247,
      "val_det_per_task": [
        0.5,
        0.5,
        0.5
      ],
      "val_det_mean": 0.5,
      "val_pfa_per_task": [
        1.0,
        1.0,
        1.0
      ],
      "val_pfa_mean": 1.0,
      "test_per_task": [],
      "test_mean": NaN,
      "test_det_per_task": [],
      "test_det_mean": NaN,
      "test_pfa_per_task": [],
      "test_pfa_mean": NaN,
      "score": 0.06122503705860247,
      "duration_sec": 91.7569146156311
    },
    {
      "status": "ok",
      "trial": 47,
      "log_dir": "logs/tuning/ucl/2026-04-01_19-26-40-1637/runs/ucl_bresnet/tuning_sweep_CIL_tune_047_beta-2em02_lr-1em05-2026-04-01_19-26-40-1637-trial047/0",
      "tf_dir": "logs/tuning/ucl/2026-04-01_19-26-40-1637/runs/ucl_bresnet/tuning_sweep_CIL_tune_047_beta-2em02_lr-1em05-2026-04-01_19-26-40-1637-trial047/0/tfdir",
      "params": {
        "beta": 0.02,
        "lr": 1e-05
      },
      "trial_params": {
        "beta": 0.02,
        "lr": 1e-05
      },
      "fixed_params": {},
      "val_per_task": [
        0.2968495488166809,
        0.09646464884281158,
        0.0
      ],
      "val_mean": 0.13110473255316415,
      "val_f1_mean": 0.05484112196290634,
      "val_det_per_task": [
        0.5,
        0.5,
        0.5
      ],
      "val_det_mean": 0.5,
      "val_pfa_per_task": [
        1.0,
        1.0,
        1.0
      ],
      "val_pfa_mean": 1.0,
      "test_per_task": [],
      "test_mean": NaN,
      "test_det_per_task": [],
      "test_det_mean": NaN,
      "test_pfa_per_task": [],
      "test_pfa_mean": NaN,
      "score": 0.05484112196290634,
      "duration_sec": 95.095041513443
    },
    {
      "status": "ok",
      "trial": 48,
      "log_dir": "logs/tuning/ucl/2026-04-01_19-26-40-1637/runs/ucl_bresnet/tuning_sweep_CIL_tune_048_beta-5em02_lr-3em02-2026-04-01_19-26-40-1637-trial048/0",
      "tf_dir": "logs/tuning/ucl/2026-04-01_19-26-40-1637/runs/ucl_bresnet/tuning_sweep_CIL_tune_048_beta-5em02_lr-3em02-2026-04-01_19-26-40-1637-trial048/0/tfdir",
      "params": {
        "beta": 0.05,
        "lr": 0.03
      },
      "trial_params": {
        "beta": 0.05,
        "lr": 0.03
      },
      "fixed_params": {},
      "val_per_task": [
        0.2864146828651428,
        0.0,
        0.0
      ],
      "val_mean": 0.09547156095504761,
      "val_f1_mean": 0.04126424012861921,
      "val_det_per_task": [
        0.5,
        0.5,
        0.5
      ],
      "val_det_mean": 0.5,
      "val_pfa_per_task": [
        1.0,
        1.0,
        1.0
      ],
      "val_pfa_mean": 1.0,
      "test_per_task": [],
      "test_mean": NaN,
      "test_det_per_task": [],
      "test_det_mean": NaN,
      "test_pfa_per_task": [],
      "test_pfa_mean": NaN,
      "score": 0.04126424012861921,
      "duration_sec": 92.46499800682068
    },
    {
      "status": "ok",
      "trial": 49,
      "log_dir": "logs/tuning/ucl/2026-04-01_19-26-40-1637/runs/ucl_bresnet/tuning_sweep_CIL_tune_049_beta-5em02_lr-1em02-2026-04-01_19-26-40-1637-trial049/0",
      "tf_dir": "logs/tuning/ucl/2026-04-01_19-26-40-1637/runs/ucl_bresnet/tuning_sweep_CIL_tune_049_beta-5em02_lr-1em02-2026-04-01_19-26-40-1637-trial049/0/tfdir",
      "params": {
        "beta": 0.05,
        "lr": 0.01
      },
      "trial_params": {
        "beta": 0.05,
        "lr": 0.01
      },
      "fixed_params": {},
      "val_per_task": [
        0.31539174914360046,
        0.07537572085857391,
        0.0
      ],
      "val_mean": 0.13025582333405814,
      "val_f1_mean": 0.05974124624887042,
      "val_det_per_task": [
        0.5,
        0.5,
        0.5
      ],
      "val_det_mean": 0.5,
      "val_pfa_per_task": [
        1.0,
        1.0,
        1.0
      ],
      "val_pfa_mean": 1.0,
      "test_per_task": [],
      "test_mean": NaN,
      "test_det_per_task": [],
      "test_det_mean": NaN,
      "test_pfa_per_task": [],
      "test_pfa_mean": NaN,
      "score": 0.05974124624887042,
      "duration_sec": 92.50621366500854
    },
    {
      "status": "ok",
      "trial": 50,
      "log_dir": "logs/tuning/ucl/2026-04-01_19-26-40-1637/runs/ucl_bresnet/tuning_sweep_CIL_tune_050_beta-5em02_lr-3em03-2026-04-01_19-26-40-1637-trial050/0",
      "tf_dir": "logs/tuning/ucl/2026-04-01_19-26-40-1637/runs/ucl_bresnet/tuning_sweep_CIL_tune_050_beta-5em02_lr-3em03-2026-04-01_19-26-40-1637-trial050/0/tfdir",
      "params": {
        "beta": 0.05,
        "lr": 0.003
      },
      "trial_params": {
        "beta": 0.05,
        "lr": 0.003
      },
      "fixed_params": {},
      "val_per_task": [
        0.3156282901763916,
        0.09646464884281158,
        0.0
      ],
      "val_mean": 0.13736431300640106,
      "val_f1_mean": 0.04935773213385102,
      "val_det_per_task": [
        0.5,
        0.5,
        0.5
      ],
      "val_det_mean": 0.5,
      "val_pfa_per_task": [
        1.0,
        1.0,
        1.0
      ],
      "val_pfa_mean": 1.0,
      "test_per_task": [],
      "test_mean": NaN,
      "test_det_per_task": [],
      "test_det_mean": NaN,
      "test_pfa_per_task": [],
      "test_pfa_mean": NaN,
      "score": 0.04935773213385102,
      "duration_sec": 94.15670323371887
    },
    {
      "status": "ok",
      "trial": 51,
      "log_dir": "logs/tuning/ucl/2026-04-01_19-26-40-1637/runs/ucl_bresnet/tuning_sweep_CIL_tune_051_beta-5em02_lr-1em03-2026-04-01_19-26-40-1637-trial051/0",
      "tf_dir": "logs/tuning/ucl/2026-04-01_19-26-40-1637/runs/ucl_bresnet/tuning_sweep_CIL_tune_051_beta-5em02_lr-1em03-2026-04-01_19-26-40-1637-trial051/0/tfdir",
      "params": {
        "beta": 0.05,
        "lr": 0.001
      },
      "trial_params": {
        "beta": 0.05,
        "lr": 0.001
      },
      "fixed_params": {},
      "val_per_task": [
        0.3366619944572449,
        0.10228897631168365,
        0.0
      ],
      "val_mean": 0.1463169902563095,
      "val_f1_mean": 0.0715615433721397,
      "val_det_per_task": [
        0.5,
        0.5,
        0.5
      ],
      "val_det_mean": 0.5,
      "val_pfa_per_task": [
        1.0,
        1.0,
        1.0
      ],
      "val_pfa_mean": 1.0,
      "test_per_task": [],
      "test_mean": NaN,
      "test_det_per_task": [],
      "test_det_mean": NaN,
      "test_pfa_per_task": [],
      "test_pfa_mean": NaN,
      "score": 0.0715615433721397,
      "duration_sec": 93.27533149719238
    },
    {
      "status": "ok",
      "trial": 52,
      "log_dir": "logs/tuning/ucl/2026-04-01_19-26-40-1637/runs/ucl_bresnet/tuning_sweep_CIL_tune_052_beta-5em02_lr-3em04-2026-04-01_19-26-40-1637-trial052/0",
      "tf_dir": "logs/tuning/ucl/2026-04-01_19-26-40-1637/runs/ucl_bresnet/tuning_sweep_CIL_tune_052_beta-5em02_lr-3em04-2026-04-01_19-26-40-1637-trial052/0/tfdir",
      "params": {
        "beta": 0.05,
        "lr": 0.0003
      },
      "trial_params": {
        "beta": 0.05,
        "lr": 0.0003
      },
      "fixed_params": {},
      "val_per_task": [
        0.3419647514820099,
        0.026355236768722534,
        0.0
      ],
      "val_mean": 0.12277332941691081,
      "val_f1_mean": 0.040374370740163076,
      "val_det_per_task": [
        0.5,
        0.5,
        0.5
      ],
      "val_det_mean": 0.5,
      "val_pfa_per_task": [
        1.0,
        1.0,
        1.0
      ],
      "val_pfa_mean": 1.0,
      "test_per_task": [],
      "test_mean": NaN,
      "test_det_per_task": [],
      "test_det_mean": NaN,
      "test_pfa_per_task": [],
      "test_pfa_mean": NaN,
      "score": 0.040374370740163076,
      "duration_sec": 91.14544463157654
    },
    {
      "status": "ok",
      "trial": 53,
      "log_dir": "logs/tuning/ucl/2026-04-01_19-26-40-1637/runs/ucl_bresnet/tuning_sweep_CIL_tune_053_beta-5em02_lr-1em04-2026-04-01_19-26-40-1637-trial053/0",
      "tf_dir": "logs/tuning/ucl/2026-04-01_19-26-40-1637/runs/ucl_bresnet/tuning_sweep_CIL_tune_053_beta-5em02_lr-1em04-2026-04-01_19-26-40-1637-trial053/0/tfdir",
      "params": {
        "beta": 0.05,
        "lr": 0.0001
      },
      "trial_params": {
        "beta": 0.05,
        "lr": 0.0001
      },
      "fixed_params": {},
      "val_per_task": [
        0.3550322949886322,
        0.09042230993509293,
        0.0
      ],
      "val_mean": 0.14848486830790839,
      "val_f1_mean": 0.05032823183423832,
      "val_det_per_task": [
        0.5,
        0.5,
        0.5
      ],
      "val_det_mean": 0.5,
      "val_pfa_per_task": [
        1.0,
        1.0,
        1.0
      ],
      "val_pfa_mean": 1.0,
      "test_per_task": [],
      "test_mean": NaN,
      "test_det_per_task": [],
      "test_det_mean": NaN,
      "test_pfa_per_task": [],
      "test_pfa_mean": NaN,
      "score": 0.05032823183423832,
      "duration_sec": 93.14272952079773
    },
    {
      "status": "ok",
      "trial": 54,
      "log_dir": "logs/tuning/ucl/2026-04-01_19-26-40-1637/runs/ucl_bresnet/tuning_sweep_CIL_tune_054_beta-5em02_lr-3em05-2026-04-01_19-26-40-1637-trial054/0",
      "tf_dir": "logs/tuning/ucl/2026-04-01_19-26-40-1637/runs/ucl_bresnet/tuning_sweep_CIL_tune_054_beta-5em02_lr-3em05-2026-04-01_19-26-40-1637-trial054/0/tfdir",
      "params": {
        "beta": 0.05,
        "lr": 3e-05
      },
      "trial_params": {
        "beta": 0.05,
        "lr": 3e-05
      },
      "fixed_params": {},
      "val_per_task": [
        0.2947627902030945,
        0.09698937088251114,
        0.0
      ],
      "val_mean": 0.13058405369520187,
      "val_f1_mean": 0.061148720980707616,
      "val_det_per_task": [
        0.5,
        0.5,
        0.5
      ],
      "val_det_mean": 0.5,
      "val_pfa_per_task": [
        1.0,
        1.0,
        1.0
      ],
      "val_pfa_mean": 1.0,
      "test_per_task": [],
      "test_mean": NaN,
      "test_det_per_task": [],
      "test_det_mean": NaN,
      "test_pfa_per_task": [],
      "test_pfa_mean": NaN,
      "score": 0.061148720980707616,
      "duration_sec": 93.99195766448975
    },
    {
      "status": "ok",
      "trial": 55,
      "log_dir": "logs/tuning/ucl/2026-04-01_19-26-40-1637/runs/ucl_bresnet/tuning_sweep_CIL_tune_055_beta-5em02_lr-1em05-2026-04-01_19-26-40-1637-trial055/0",
      "tf_dir": "logs/tuning/ucl/2026-04-01_19-26-40-1637/runs/ucl_bresnet/tuning_sweep_CIL_tune_055_beta-5em02_lr-1em05-2026-04-01_19-26-40-1637-trial055/0/tfdir",
      "params": {
        "beta": 0.05,
        "lr": 1e-05
      },
      "trial_params": {
        "beta": 0.05,
        "lr": 1e-05
      },
      "fixed_params": {},
      "val_per_task": [
        0.2968495488166809,
        0.09646464884281158,
        0.0
      ],
      "val_mean": 0.13110473255316415,
      "val_f1_mean": 0.054674757579673466,
      "val_det_per_task": [
        0.5,
        0.5,
        0.5
      ],
      "val_det_mean": 0.5,
      "val_pfa_per_task": [
        1.0,
        1.0,
        1.0
      ],
      "val_pfa_mean": 1.0,
      "test_per_task": [],
      "test_mean": NaN,
      "test_det_per_task": [],
      "test_det_mean": NaN,
      "test_pfa_per_task": [],
      "test_pfa_mean": NaN,
      "score": 0.054674757579673466,
      "duration_sec": 92.47118353843689
    },
    {
      "status": "ok",
      "trial": 56,
      "log_dir": "logs/tuning/ucl/2026-04-01_19-26-40-1637/runs/ucl_bresnet/tuning_sweep_CIL_tune_056_beta-1em01_lr-3em02-2026-04-01_19-26-40-1637-trial056/0",
      "tf_dir": "logs/tuning/ucl/2026-04-01_19-26-40-1637/runs/ucl_bresnet/tuning_sweep_CIL_tune_056_beta-1em01_lr-3em02-2026-04-01_19-26-40-1637-trial056/0/tfdir",
      "params": {
        "beta": 0.1,
        "lr": 0.03
      },
      "trial_params": {
        "beta": 0.1,
        "lr": 0.03
      },
      "fixed_params": {},
      "val_per_task": [
        0.4204547703266144,
        0.0,
        0.0
      ],
      "val_mean": 0.14015159010887146,
      "val_f1_mean": 0.058528254192929875,
      "val_det_per_task": [
        0.5,
        0.5,
        0.5
      ],
      "val_det_mean": 0.5,
      "val_pfa_per_task": [
        1.0,
        1.0,
        1.0
      ],
      "val_pfa_mean": 1.0,
      "test_per_task": [],
      "test_mean": NaN,
      "test_det_per_task": [],
      "test_det_mean": NaN,
      "test_pfa_per_task": [],
      "test_pfa_mean": NaN,
      "score": 0.058528254192929875,
      "duration_sec": 93.53992748260498
    },
    {
      "status": "ok",
      "trial": 57,
      "log_dir": "logs/tuning/ucl/2026-04-01_19-26-40-1637/runs/ucl_bresnet/tuning_sweep_CIL_tune_057_beta-1em01_lr-1em02-2026-04-01_19-26-40-1637-trial057/0",
      "tf_dir": "logs/tuning/ucl/2026-04-01_19-26-40-1637/runs/ucl_bresnet/tuning_sweep_CIL_tune_057_beta-1em01_lr-1em02-2026-04-01_19-26-40-1637-trial057/0/tfdir",
      "params": {
        "beta": 0.1,
        "lr": 0.01
      },
      "trial_params": {
        "beta": 0.1,
        "lr": 0.01
      },
      "fixed_params": {},
      "val_per_task": [
        0.3414149582386017,
        0.0,
        0.0
      ],
      "val_mean": 0.11380498607953389,
      "val_f1_mean": 0.03762476417084199,
      "val_det_per_task": [
        0.5,
        0.5,
        0.5
      ],
      "val_det_mean": 0.5,
      "val_pfa_per_task": [
        1.0,
        1.0,
        1.0
      ],
      "val_pfa_mean": 1.0,
      "test_per_task": [],
      "test_mean": NaN,
      "test_det_per_task": [],
      "test_det_mean": NaN,
      "test_pfa_per_task": [],
      "test_pfa_mean": NaN,
      "score": 0.03762476417084199,
      "duration_sec": 92.66282677650452
    },
    {
      "status": "ok",
      "trial": 58,
      "log_dir": "logs/tuning/ucl/2026-04-01_19-26-40-1637/runs/ucl_bresnet/tuning_sweep_CIL_tune_058_beta-1em01_lr-3em03-2026-04-01_19-26-40-1637-trial058/0",
      "tf_dir": "logs/tuning/ucl/2026-04-01_19-26-40-1637/runs/ucl_bresnet/tuning_sweep_CIL_tune_058_beta-1em01_lr-3em03-2026-04-01_19-26-40-1637-trial058/0/tfdir",
      "params": {
        "beta": 0.1,
        "lr": 0.003
      },
      "trial_params": {
        "beta": 0.1,
        "lr": 0.003
      },
      "fixed_params": {},
      "val_per_task": [
        0.3001565933227539,
        0.09646464884281158,
        0.0
      ],
      "val_mean": 0.13220708072185516,
      "val_f1_mean": 0.04869500262877124,
      "val_det_per_task": [
        0.5,
        0.5,
        0.5
      ],
      "val_det_mean": 0.5,
      "val_pfa_per_task": [
        1.0,
        1.0,
        1.0
      ],
      "val_pfa_mean": 1.0,
      "test_per_task": [],
      "test_mean": NaN,
      "test_det_per_task": [],
      "test_det_mean": NaN,
      "test_pfa_per_task": [],
      "test_pfa_mean": NaN,
      "score": 0.04869500262877124,
      "duration_sec": 92.94245433807373
    },
    {
      "status": "ok",
      "trial": 59,
      "log_dir": "logs/tuning/ucl/2026-04-01_19-26-40-1637/runs/ucl_bresnet/tuning_sweep_CIL_tune_059_beta-1em01_lr-1em03-2026-04-01_19-26-40-1637-trial059/0",
      "tf_dir": "logs/tuning/ucl/2026-04-01_19-26-40-1637/runs/ucl_bresnet/tuning_sweep_CIL_tune_059_beta-1em01_lr-1em03-2026-04-01_19-26-40-1637-trial059/0/tfdir",
      "params": {
        "beta": 0.1,
        "lr": 0.001
      },
      "trial_params": {
        "beta": 0.1,
        "lr": 0.001
      },
      "fixed_params": {},
      "val_per_task": [
        0.33940279483795166,
        0.10860901325941086,
        0.0
      ],
      "val_mean": 0.1493372693657875,
      "val_f1_mean": 0.0788141086440622,
      "val_det_per_task": [
        0.5,
        0.5,
        0.5
      ],
      "val_det_mean": 0.5,
      "val_pfa_per_task": [
        1.0,
        1.0,
        1.0
      ],
      "val_pfa_mean": 1.0,
      "test_per_task": [],
      "test_mean": NaN,
      "test_det_per_task": [],
      "test_det_mean": NaN,
      "test_pfa_per_task": [],
      "test_pfa_mean": NaN,
      "score": 0.0788141086440622,
      "duration_sec": 92.04697823524475
    },
    {
      "status": "ok",
      "trial": 60,
      "log_dir": "logs/tuning/ucl/2026-04-01_19-26-40-1637/runs/ucl_bresnet/tuning_sweep_CIL_tune_060_beta-1em01_lr-3em04-2026-04-01_19-26-40-1637-trial060/0",
      "tf_dir": "logs/tuning/ucl/2026-04-01_19-26-40-1637/runs/ucl_bresnet/tuning_sweep_CIL_tune_060_beta-1em01_lr-3em04-2026-04-01_19-26-40-1637-trial060/0/tfdir",
      "params": {
        "beta": 0.1,
        "lr": 0.0003
      },
      "trial_params": {
        "beta": 0.1,
        "lr": 0.0003
      },
      "fixed_params": {},
      "val_per_task": [
        0.35156744718551636,
        0.027171844616532326,
        0.0
      ],
      "val_mean": 0.12624643060068289,
      "val_f1_mean": 0.041463579629083175,
      "val_det_per_task": [
        0.5,
        0.5,
        0.5
      ],
      "val_det_mean": 0.5,
      "val_pfa_per_task": [
        1.0,
        1.0,
        1.0
      ],
      "val_pfa_mean": 1.0,
      "test_per_task": [],
      "test_mean": NaN,
      "test_det_per_task": [],
      "test_det_mean": NaN,
      "test_pfa_per_task": [],
      "test_pfa_mean": NaN,
      "score": 0.041463579629083175,
      "duration_sec": 91.66665816307068
    },
    {
      "status": "ok",
      "trial": 61,
      "log_dir": "logs/tuning/ucl/2026-04-01_19-26-40-1637/runs/ucl_bresnet/tuning_sweep_CIL_tune_061_beta-1em01_lr-1em04-2026-04-01_19-26-40-1637-trial061/0",
      "tf_dir": "logs/tuning/ucl/2026-04-01_19-26-40-1637/runs/ucl_bresnet/tuning_sweep_CIL_tune_061_beta-1em01_lr-1em04-2026-04-01_19-26-40-1637-trial061/0/tfdir",
      "params": {
        "beta": 0.1,
        "lr": 0.0001
      },
      "trial_params": {
        "beta": 0.1,
        "lr": 0.0001
      },
      "fixed_params": {},
      "val_per_task": [
        0.3550322949886322,
        0.0894286036491394,
        0.0
      ],
      "val_mean": 0.1481536328792572,
      "val_f1_mean": 0.05010174559490946,
      "val_det_per_task": [
        0.5,
        0.5,
        0.5
      ],
      "val_det_mean": 0.5,
      "val_pfa_per_task": [
        1.0,
        1.0,
        1.0
      ],
      "val_pfa_mean": 1.0,
      "test_per_task": [],
      "test_mean": NaN,
      "test_det_per_task": [],
      "test_det_mean": NaN,
      "test_pfa_per_task": [],
      "test_pfa_mean": NaN,
      "score": 0.05010174559490946,
      "duration_sec": 93.49923825263977
    },
    {
      "status": "ok",
      "trial": 62,
      "log_dir": "logs/tuning/ucl/2026-04-01_19-26-40-1637/runs/ucl_bresnet/tuning_sweep_CIL_tune_062_beta-1em01_lr-3em05-2026-04-01_19-26-40-1637-trial062/0",
      "tf_dir": "logs/tuning/ucl/2026-04-01_19-26-40-1637/runs/ucl_bresnet/tuning_sweep_CIL_tune_062_beta-1em01_lr-3em05-2026-04-01_19-26-40-1637-trial062/0/tfdir",
      "params": {
        "beta": 0.1,
        "lr": 3e-05
      },
      "trial_params": {
        "beta": 0.1,
        "lr": 3e-05
      },
      "fixed_params": {},
      "val_per_task": [
        0.299306184053421,
        0.09698937088251114,
        0.0
      ],
      "val_mean": 0.1320985183119774,
      "val_f1_mean": 0.0626001514498861,
      "val_det_per_task": [
        0.5,
        0.5,
        0.5
      ],
      "val_det_mean": 0.5,
      "val_pfa_per_task": [
        1.0,
        1.0,
        1.0
      ],
      "val_pfa_mean": 1.0,
      "test_per_task": [],
      "test_mean": NaN,
      "test_det_per_task": [],
      "test_det_mean": NaN,
      "test_pfa_per_task": [],
      "test_pfa_mean": NaN,
      "score": 0.0626001514498861,
      "duration_sec": 92.68441843986511
    },
    {
      "status": "ok",
      "trial": 63,
      "log_dir": "logs/tuning/ucl/2026-04-01_19-26-40-1637/runs/ucl_bresnet/tuning_sweep_CIL_tune_063_beta-1em01_lr-1em05-2026-04-01_19-26-40-1637-trial063/0",
      "tf_dir": "logs/tuning/ucl/2026-04-01_19-26-40-1637/runs/ucl_bresnet/tuning_sweep_CIL_tune_063_beta-1em01_lr-1em05-2026-04-01_19-26-40-1637-trial063/0/tfdir",
      "params": {
        "beta": 0.1,
        "lr": 1e-05
      },
      "trial_params": {
        "beta": 0.1,
        "lr": 1e-05
      },
      "fixed_params": {},
      "val_per_task": [
        0.29970669746398926,
        0.09646464884281158,
        0.0
      ],
      "val_mean": 0.13205711543560028,
      "val_f1_mean": 0.055203455136374174,
      "val_det_per_task": [
        0.5,
        0.5,
        0.5
      ],
      "val_det_mean": 0.5,
      "val_pfa_per_task": [
        1.0,
        1.0,
        1.0
      ],
      "val_pfa_mean": 1.0,
      "test_per_task": [],
      "test_mean": NaN,
      "test_det_per_task": [],
      "test_det_mean": NaN,
      "test_pfa_per_task": [],
      "test_pfa_mean": NaN,
      "score": 0.055203455136374174,
      "duration_sec": 91.4324836730957
    },
    {
      "status": "ok",
      "trial": 64,
      "log_dir": "logs/tuning/ucl/2026-04-01_19-26-40-1637/runs/ucl_bresnet/tuning_sweep_CIL_tune_064_beta-5em01_lr-3em02-2026-04-01_19-26-40-1637-trial064/0",
      "tf_dir": "logs/tuning/ucl/2026-04-01_19-26-40-1637/runs/ucl_bresnet/tuning_sweep_CIL_tune_064_beta-5em01_lr-3em02-2026-04-01_19-26-40-1637-trial064/0/tfdir",
      "params": {
        "beta": 0.5,
        "lr": 0.03
      },
      "trial_params": {
        "beta": 0.5,
        "lr": 0.03
      },
      "fixed_params": {},
      "val_per_task": [
        0.2028571367263794,
        0.0,
        0.0
      ],
      "val_mean": 0.0676190455754598,
      "val_f1_mean": 0.01845178654095881,
      "val_det_per_task": [
        0.5,
        0.5,
        0.5
      ],
      "val_det_mean": 0.5,
      "val_pfa_per_task": [
        1.0,
        1.0,
        1.0
      ],
      "val_pfa_mean": 1.0,
      "test_per_task": [],
      "test_mean": NaN,
      "test_det_per_task": [],
      "test_det_mean": NaN,
      "test_pfa_per_task": [],
      "test_pfa_mean": NaN,
      "score": 0.01845178654095881,
      "duration_sec": 93.53442978858948
    },
    {
      "status": "ok",
      "trial": 65,
      "log_dir": "logs/tuning/ucl/2026-04-01_19-26-40-1637/runs/ucl_bresnet/tuning_sweep_CIL_tune_065_beta-5em01_lr-1em02-2026-04-01_19-26-40-1637-trial065/0",
      "tf_dir": "logs/tuning/ucl/2026-04-01_19-26-40-1637/runs/ucl_bresnet/tuning_sweep_CIL_tune_065_beta-5em01_lr-1em02-2026-04-01_19-26-40-1637-trial065/0/tfdir",
      "params": {
        "beta": 0.5,
        "lr": 0.01
      },
      "trial_params": {
        "beta": 0.5,
        "lr": 0.01
      },
      "fixed_params": {},
      "val_per_task": [
        0.3439452648162842,
        0.10079667717218399,
        0.0
      ],
      "val_mean": 0.14824731399615607,
      "val_f1_mean": 0.07217944048946663,
      "val_det_per_task": [
        0.5,
        0.5,
        0.5
      ],
      "val_det_mean": 0.5,
      "val_pfa_per_task": [
        1.0,
        1.0,
        1.0
      ],
      "val_pfa_mean": 1.0,
      "test_per_task": [],
      "test_mean": NaN,
      "test_det_per_task": [],
      "test_det_mean": NaN,
      "test_pfa_per_task": [],
      "test_pfa_mean": NaN,
      "score": 0.07217944048946663,
      "duration_sec": 92.94988560676575
    },
    {
      "status": "ok",
      "trial": 66,
      "log_dir": "logs/tuning/ucl/2026-04-01_19-26-40-1637/runs/ucl_bresnet/tuning_sweep_CIL_tune_066_beta-5em01_lr-3em03-2026-04-01_19-26-40-1637-trial066/0",
      "tf_dir": "logs/tuning/ucl/2026-04-01_19-26-40-1637/runs/ucl_bresnet/tuning_sweep_CIL_tune_066_beta-5em01_lr-3em03-2026-04-01_19-26-40-1637-trial066/0/tfdir",
      "params": {
        "beta": 0.5,
        "lr": 0.003
      },
      "trial_params": {
        "beta": 0.5,
        "lr": 0.003
      },
      "fixed_params": {},
      "val_per_task": [
        0.2598278820514679,
        0.09646464884281158,
        0.0
      ],
      "val_mean": 0.11876417696475983,
      "val_f1_mean": 0.04074988706294597,
      "val_det_per_task": [
        0.5,
        0.5,
        0.5
      ],
      "val_det_mean": 0.5,
      "val_pfa_per_task": [
        1.0,
        1.0,
        1.0
      ],
      "val_pfa_mean": 1.0,
      "test_per_task": [],
      "test_mean": NaN,
      "test_det_per_task": [],
      "test_det_mean": NaN,
      "test_pfa_per_task": [],
      "test_pfa_mean": NaN,
      "score": 0.04074988706294597,
      "duration_sec": 92.32318592071533
    },
    {
      "status": "ok",
      "trial": 67,
      "log_dir": "logs/tuning/ucl/2026-04-01_19-26-40-1637/runs/ucl_bresnet/tuning_sweep_CIL_tune_067_beta-5em01_lr-1em03-2026-04-01_19-26-40-1637-trial067/0",
      "tf_dir": "logs/tuning/ucl/2026-04-01_19-26-40-1637/runs/ucl_bresnet/tuning_sweep_CIL_tune_067_beta-5em01_lr-1em03-2026-04-01_19-26-40-1637-trial067/0/tfdir",
      "params": {
        "beta": 0.5,
        "lr": 0.001
      },
      "trial_params": {
        "beta": 0.5,
        "lr": 0.001
      },
      "fixed_params": {},
      "val_per_task": [
        0.32674771547317505,
        0.10706982016563416,
        0.0
      ],
      "val_mean": 0.1446058452129364,
      "val_f1_mean": 0.06659045699652115,
      "val_det_per_task": [
        0.5,
        0.5,
        0.5
      ],
      "val_det_mean": 0.5,
      "val_pfa_per_task": [
        1.0,
        1.0,
        1.0
      ],
      "val_pfa_mean": 1.0,
      "test_per_task": [],
      "test_mean": NaN,
      "test_det_per_task": [],
      "test_det_mean": NaN,
      "test_pfa_per_task": [],
      "test_pfa_mean": NaN,
      "score": 0.06659045699652115,
      "duration_sec": 94.46686267852783
    },
    {
      "status": "ok",
      "trial": 68,
      "log_dir": "logs/tuning/ucl/2026-04-01_19-26-40-1637/runs/ucl_bresnet/tuning_sweep_CIL_tune_068_beta-5em01_lr-3em04-2026-04-01_19-26-40-1637-trial068/0",
      "tf_dir": "logs/tuning/ucl/2026-04-01_19-26-40-1637/runs/ucl_bresnet/tuning_sweep_CIL_tune_068_beta-5em01_lr-3em04-2026-04-01_19-26-40-1637-trial068/0/tfdir",
      "params": {
        "beta": 0.5,
        "lr": 0.0003
      },
      "trial_params": {
        "beta": 0.5,
        "lr": 0.0003
      },
      "fixed_params": {},
      "val_per_task": [
        0.34548744559288025,
        0.03042679652571678,
        0.0
      ],
      "val_mean": 0.12530474737286568,
      "val_f1_mean": 0.04046678557093821,
      "val_det_per_task": [
        0.5,
        0.5,
        0.5
      ],
      "val_det_mean": 0.5,
      "val_pfa_per_task": [
        1.0,
        1.0,
        1.0
      ],
      "val_pfa_mean": 1.0,
      "test_per_task": [],
      "test_mean": NaN,
      "test_det_per_task": [],
      "test_det_mean": NaN,
      "test_pfa_per_task": [],
      "test_pfa_mean": NaN,
      "score": 0.04046678557093821,
      "duration_sec": 93.03465819358826
    },
    {
      "status": "ok",
      "trial": 69,
      "log_dir": "logs/tuning/ucl/2026-04-01_19-26-40-1637/runs/ucl_bresnet/tuning_sweep_CIL_tune_069_beta-5em01_lr-1em04-2026-04-01_19-26-40-1637-trial069/0",
      "tf_dir": "logs/tuning/ucl/2026-04-01_19-26-40-1637/runs/ucl_bresnet/tuning_sweep_CIL_tune_069_beta-5em01_lr-1em04-2026-04-01_19-26-40-1637-trial069/0/tfdir",
      "params": {
        "beta": 0.5,
        "lr": 0.0001
      },
      "trial_params": {
        "beta": 0.5,
        "lr": 0.0001
      },
      "fixed_params": {},
      "val_per_task": [
        0.3576989769935608,
        0.09013821929693222,
        0.0
      ],
      "val_mean": 0.14927906543016434,
      "val_f1_mean": 0.0506446150227988,
      "val_det_per_task": [
        0.5,
        0.5,
        0.5
      ],
      "val_det_mean": 0.5,
      "val_pfa_per_task": [
        1.0,
        1.0,
        1.0
      ],
      "val_pfa_mean": 1.0,
      "test_per_task": [],
      "test_mean": NaN,
      "test_det_per_task": [],
      "test_det_mean": NaN,
      "test_pfa_per_task": [],
      "test_pfa_mean": NaN,
      "score": 0.0506446150227988,
      "duration_sec": 92.4515733718872
    },
    {
      "status": "ok",
      "trial": 70,
      "log_dir": "logs/tuning/ucl/2026-04-01_19-26-40-1637/runs/ucl_bresnet/tuning_sweep_CIL_tune_070_beta-5em01_lr-3em05-2026-04-01_19-26-40-1637-trial070/0",
      "tf_dir": "logs/tuning/ucl/2026-04-01_19-26-40-1637/runs/ucl_bresnet/tuning_sweep_CIL_tune_070_beta-5em01_lr-3em05-2026-04-01_19-26-40-1637-trial070/0/tfdir",
      "params": {
        "beta": 0.5,
        "lr": 3e-05
      },
      "trial_params": {
        "beta": 0.5,
        "lr": 3e-05
      },
      "fixed_params": {},
      "val_per_task": [
        0.3033061921596527,
        0.09698937088251114,
        0.0
      ],
      "val_mean": 0.13343185434738794,
      "val_f1_mean": 0.0626719478246935,
      "val_det_per_task": [
        0.5,
        0.5,
        0.5
      ],
      "val_det_mean": 0.5,
      "val_pfa_per_task": [
        1.0,
        1.0,
        1.0
      ],
      "val_pfa_mean": 1.0,
      "test_per_task": [],
      "test_mean": NaN,
      "test_det_per_task": [],
      "test_det_mean": NaN,
      "test_pfa_per_task": [],
      "test_pfa_mean": NaN,
      "score": 0.0626719478246935,
      "duration_sec": 93.83520531654358
    },
    {
      "status": "ok",
      "trial": 71,
      "log_dir": "logs/tuning/ucl/2026-04-01_19-26-40-1637/runs/ucl_bresnet/tuning_sweep_CIL_tune_071_beta-5em01_lr-1em05-2026-04-01_19-26-40-1637-trial071/0",
      "tf_dir": "logs/tuning/ucl/2026-04-01_19-26-40-1637/runs/ucl_bresnet/tuning_sweep_CIL_tune_071_beta-5em01_lr-1em05-2026-04-01_19-26-40-1637-trial071/0/tfdir",
      "params": {
        "beta": 0.5,
        "lr": 1e-05
      },
      "trial_params": {
        "beta": 0.5,
        "lr": 1e-05
      },
      "fixed_params": {},
      "val_per_task": [
        0.2971632778644562,
        0.09646464884281158,
        0.0
      ],
      "val_mean": 0.13120930890242258,
      "val_f1_mean": 0.054732746366123304,
      "val_det_per_task": [
        0.5,
        0.5,
        0.5
      ],
      "val_det_mean": 0.5,
      "val_pfa_per_task": [
        1.0,
        1.0,
        1.0
      ],
      "val_pfa_mean": 1.0,
      "test_per_task": [],
      "test_mean": NaN,
      "test_det_per_task": [],
      "test_det_mean": NaN,
      "test_pfa_per_task": [],
      "test_pfa_mean": NaN,
      "score": 0.054732746366123304,
      "duration_sec": 93.58625507354736
    }
  ],
  "best": {
    "status": "ok",
    "trial": 59,
    "log_dir": "logs/tuning/ucl/2026-04-01_19-26-40-1637/runs/ucl_bresnet/tuning_sweep_CIL_tune_059_beta-1em01_lr-1em03-2026-04-01_19-26-40-1637-trial059/0",
    "tf_dir": "logs/tuning/ucl/2026-04-01_19-26-40-1637/runs/ucl_bresnet/tuning_sweep_CIL_tune_059_beta-1em01_lr-1em03-2026-04-01_19-26-40-1637-trial059/0/tfdir",
    "params": {
      "beta": 0.1,
      "lr": 0.001
    },
    "trial_params": {
      "beta": 0.1,
      "lr": 0.001
    },
    "fixed_params": {},
    "val_per_task": [
      0.33940279483795166,
      0.10860901325941086,
      0.0
    ],
    "val_mean": 0.1493372693657875,
    "val_f1_mean": 0.0788141086440622,
    "val_det_per_task": [
      0.5,
      0.5,
      0.5
    ],
    "val_det_mean": 0.5,
    "val_pfa_per_task": [
      1.0,
      1.0,
      1.0
    ],
    "val_pfa_mean": 1.0,
    "test_per_task": [],
    "test_mean": NaN,
    "test_det_per_task": [],
    "test_det_mean": NaN,
    "test_pfa_per_task": [],
    "test_pfa_mean": NaN,
    "score": 0.0788141086440622,
    "duration_sec": 92.04697823524475
  }
}